Workbook

Sheet Analysis
A3: Row Labels | B3: Average of AVE Departure | E3: Row Labels | F3: Average of AVE Departure | H3: Row Labels | I3: Average of AVE Departure | J3: Tar
A4: January | B4: 44.994912 | E4: January | F4: 44.994912 | H4: October | I4: 46.609851 | J4: 45
A5: September | B5: 44.480208 | E5: September | F5: 44.480208 | H5: November | I5: 48.502326 | J5: 45
A6: October | B6: 46.609851 | E6: October | F6: 46.609851 | H6: December | I6: 47.503878 | J6: 45
A7: November | B7: 48.502326 | E7: November | F7: 48.502326 | H7: January | I7: 44.994912 | J7: 45
A8: December | B8: 47.503878 | E8: December | F8: 47.503878 | H8: Quarter | I8: =AVERAGE(I4:I7) -> 46.902742 | J8: 45
A9: (blank) | E9: (blank)
A10: Grand Total | B10: 46.929042 | E10: Grand Total | F10: 46.929042
E22: Row Labels | F22: October | G22: November | H22: December | I22: January
E23: Damaged stock replacement | F23: 58.733333 | G23: 59.225 | H23: 59.388889 | I23: 46.016667
E24: Delayed Check ins | F24: 54.336111 | G24: 57.763333 | H24: 55.52619 | I24: 50.769048
E25: Delayed order capture | F25: 47.105882 | G25: 47.673188 | H25: 47.701515 | I25: 51.809722
E26: DJ failures | F26: 57.527451 | G26: 51.883333 | H26: 52.757407 | I26: 54.12619
E27: Driver delays | F27: 56.645238 | G27: 56.05 | H27: 55.528571 | I27: 51.522917
E28: Late coming | F28: 60.044444 | G28: 54.714815 | H28: 58.246667 | I28: 50.175
E29: Pre-Trip inspection defect closure | F29: 63.516667 | G29: 70.853086 | H29: 59.505882 | I29: 58.347619
E30: Prolonged meeting. | G30: 60.044444 | H30: 59.225
E31: Reconcile stock count delays | F31: 58.25 | G31: 59.80303 | H31: 57.9 | I31: 54.426667
E32: Traffic at the exit gate. | G32: 59.154762 | H32: 59.448485
E33: unplanned trainings | F33: 54.046667 | G33: 55.805556 | H33: 55.809524 | I33: 51.885714
E34: Weigh bridge delays | F34: 59.225 | G34: 59.323333 | H34: 59.022549 | I34: 55.8
E35: Grand Total | F35: =AVERAGE(F23:F34) -> 56.943079 | G35: =AVERAGE(G23:G34) -> 57.691157 | H35: =AVERAGE(H23:H34) -> 56.671723 | I35: =AVERAGE(I23:I34) -> 52.487954

Sheet LIST 2
A1: CUSTOMER NAME | B1: KM 1 WAY | C1: KM 2 WAY | D1: DAYS IN TRADE | E1: POC TIME
A2: Kabaco U Ltd-Mbarara Tax No.: 1000025425 | B2: 10 | C2: =B2*2 -> 20 | D2: 1 | E2: 3
A3: Kabaco U Ltd Tax No.: 1000025425 | B3: 152 | C3: =B3*2 -> 304 | D3: 2 | E3: 3
A4: KATO INVESTMENTS LTD- KALISIZO Tax No.: 1000098824 | B4: 144 | C4: =B4*2 -> 288 | D4: 2 | E4: 3
A5: KATO INVESTMENTS LIMITED-MASAK Tax No.: 1000098824 | B5: 298 | C5: =B5*2 -> 596 | D5: 2 | E5: 3
A6: RUGOMA TRADERS CO. LTD NTUNGAM Tax No.: 1000249350 | B6: 75 | C6: =B6*2 -> 150 | D6: 1 | E6: 3
A7: Rugoma Traders-Kanungu/Kihihi Tax No.: 1000249350 | B7: 136 | C7: =B7*2 -> 272 | D7: 2 | E7: 3
A8: Boniface Harera Tax No.: 1000317747 | B8: 224 | C8: =B8*2 -> 448 | D8: 2 | E8: 3
A9: Bates Enterprises Ltd-Ntoroko Tax No.: 1001193253 | B9: 255 | C9: =B9*2 -> 510 | D9: 3 | E9: 3
A10: Sawan Distributors Ltd-Nabingo Tax No.: 1000186379 | B10: 280 | C10: =B10*2 -> 560 | D10: 2 | E10: 3
A11: Rugoma Traders-Rukungiri Tax No.: 1000249350 | B11: 128 | C11: =B11*2 -> 256 | D11: 2 | E11: 3
A12: Kobusinge Acaali- Kyenjojo Tax No.: 1000977837 | B12: 290 | C12: =B12*2 -> 580 | D12: 2 | E12: 3
A13: Kato Investments Ltd- Kakumiro Tax No.: 1000098824 | B13: 395 | C13: =B13*2 -> 790 | D13: 3 | E13: 3
... A28: Kachain Logistics Ltd Tax No.: 1005388662 | B28: 280 | C28: =B28*2 -> 560 | D28: 3 | E28: 3

Sheet Sheet2
N1: Month Name | O1: (All) | Q1: Row Labels | R1: Average of Total Hour Route
D2: Month Name | E2: (All) | G2: Average of AVE Departure | H2: Column Labels | Q2: January | R2: 40.935924
G3: Row Labels | H3: January | I3: February | J3: March | K3: April | L3: Grand Total | N3: Row Labels | O3: Count of Comment AVE Departure | Q3: February | R3: 42.306507
A4: Row Labels | B4: Average of AVE Departure | C4: TAR | D4: Row Labels | E4: Average of AVE Departure | G4: Mbogo bashil | J4: 23.888889 | L4: 23.888889 | N4: DJ failures | O4: 20 | Q4: March | R4: 41.509128 | W4: Row Labels | X4: Average of AVE Arrival Time
A5: January | B5: 43.986135 | C5: 45 | D5: Mbogo bashil | E5: 23.888889 | G5: Awali Malinzi | J5: 26.078704 | L5: 26.078704 | N5: Jam at the weigh bridge | O5: 12 | Q5: April | R5: 39.488205 | W5: January | X5: 55.873067
A6: February | B6: 42.703066 | C6: 45 | D6: Muzamiru | E6: 25.87963 | G6: Kyapa Hakim | J6: 26.875 | L6: 26.875 | N6: Pre-Trip inspection defect closure | O6: 10 | Q6: Grand Total | R6: 41.420317 | W6: February | X6: 55.160639
A7: March | B7: 30.284293 | C7: 45 | D7: Awali Malinzi | E7: 26.078704 | G7: kakembo Masudi | I7: 42.966821 | J7: 26.21142 | L7: 32.91358 | N7: Unplanned Training | O7: 3 | W7: March | X7: 50.415357
A8: April | B8: 32.349537 | D8: Kyapa Hakim | E8: 26.875 | G8: Malinzi Awali | I8: 43.298611 | J8: 27.87037 | L8: 33.013117 | N8: Reconciling stock count delays | O8: 3 | W8: April | X8: 43.158654
A9: Grand Total | B9: 37.530567 | D9: kakembo Masudi | E9: 32.91358 | G9: Ikwalikwa Yusuf | I9: 42.137346 | J9: 26.626157 | L9: 33.27381 | N9: Meeting Delays | O9: 2 | W9: Grand Total | X9: 52.195184
D10: Malinzi Awali | E10: 33.013117 | G10: Faruk Abel | I10: 42.089947 | J10: 28.423354 | L10: 34.402488 | N10: Driver delays | O10: 1
A11: Month | B11: AVE departure | C11: Tar | D11: Ikwalikwa Yusuf | E11: 33.27381 | G11: Stephen Musoke | H11: 41.407407 | I11: 42.65873 | J11: 27.273148 | K11: 26.54321 | L11: 34.837963 | N11: Damaged stock replacement | O11: 1
A12: January | B12: 43.986135 | C12: 45 | D12: Faruk Abel | E12: 34.402488 | G12: Kabene John | H12: 41.30787 | I12: 41.916152 | J12: 33.842593 | K12: 27.779882 | L12: 35.122354 | N12: Grand Total | O12: 52
A13: February | B13: 42.879726 | C13: 45 | D13: Stephen Musoke | E13: 34.837963 | G13: Bisaso Ronald | H13: 43.049769 | I13: 41.606481 | J13: 26.875 | K13: 27.87037 | L13: 35.423475
A14: March | B14: 42.669737 | C14: 45 | D14: Kabene John | E14: 35.122354 | G14: Abel Mark naffa | H14: 39.814815 | I14: 42.137346 | J14: 27.87037 | K14: 31.851852 | L14: 35.594444
A15: quarter | B15: =AVERAGE(B12:B14) -> 43.178533 | C15: =AVERAGE(C12:C14) -> 45 | D15: Bisaso Ronald | E15: 35.423475 | G15: Lule Fred | I15: 42.552083 | J15: 27.20679 | L15: 35.975529
D16: Abel Mark naffa | E16: 35.594444 | G16: Nassasira | J16: 36.165123 | L16: 36.165123
D17: Lule Fred | E17: 35.975529 | G17: Nminya Siraje | I17: 41.681134 | J17: 29.861111 | L17: 36.165123
D18: Nassasira | E18: 36.165123 | G18: Mulumba Kasim | I18: 42.502315 | J18: 27.159392 | L18: 36.184641
D19: Nminya Siraje | E19: 36.165123 | G19: Byanshala Stoney | I19: 42.026749 | J19: 29.985532 | L19: 36.360294
D20: Mulumba Kasim | E20: 36.184641 | G20: Mudunga Musa | I20: 42.303241 | J20: 27.621528 | L20: 36.430556
D21: Byanshala Stoney | E21: 36.360294 | G21: kayanja Sam | I21: 42.943122 | J21: 30.145503 | L21: 36.544312 | N21: Row Labels
D22: Mudunga Musa | E22: 36.430556 | G22: (blank) | H22: 44.328305 | I22: 43.154544 | J22: 28.831418 | L22: 36.780926 | N22: Damaged stock replacement
D23: kayanja Sam | E23: 36.544312 | G23: MUKOSE MUZAMIRU | H23: 40.699588 | I23: 42.203704 | K23: 26.709105 | L23: 36.878472 | N23: Delayed Check ins
D24: MUKOSE MUZAMIRU | E24: 36.878472 | G24: Kilabila Ismail | H24: 44.69213 | I24: 42.00463 | J24: 39.31713 | K24: 28.451003 | L24: 37.137612 | N24: Delayed order capture
D25: Kilabila Ismail | E25: 37.137612 | G25: Nakalya John | H25: 56.736111 | I25: 41.031379 | J25: 30.607639 | L25: 37.271091 | N25: DJ failures
D26: GODWIN NIWENSIIMA | E26: 37.160494 | G26: Matovu Musa | I26: 42.303241 | J26: 27.372685 | L26: 37.326389 | N26: Driver delays
D27: Nakalya John | E27: 37.271091 | G27: Bwanga Gilbert | I27: 41.929977 | J27: 31.685957 | L27: 37.539683 | N27: Late coming
D28: Matovu Musa | E28: 37.326389 | G28: NTUMWA SOLOMON | H28: 43.796296 | I28: 44.667245 | J28: 26.277778 | L28: 38.037368 | N28: Pre-Trip inspection defect closure
D29: Bwanga Gilbert | E29: 37.539683 | G29: Tsaale Hassan | I29: 43.464506 | J29: 32.626029 | L29: 38.045267 | N29: Prolonged meeting.
D30: NTUMWA SOLOMON | E30: 38.037368 | G30: Mugisha George | H30: 48.972222 | I30: 43.796296 | J30: 26.128472 | K30: 36.686508 | L30: 38.233932 | N30: Reconcile stock count delays
D31: Tsaale Hassan | E31: 38.045267 | G31: ZIWA ABASI | H31: 40.063657 | I31: 42.800926 | J31: 33.344907 | K31: 37.824074 | L31: 38.638468 | N31: Traffic at the exit gate.
D32: Mugisha George | E32: 38.233932 | G32: Luyaga Isaac | H32: 39.483025 | I32: 41.805556 | J32: 39.814815 | K32: 35.335648 | L32: 38.670139 | N32: unplanned trainings
D33: ZIWA ABASI | E33: 38.638468 | G33: Eriku Alipa | I33: 41.805556 | J33: 36.331019 | L33: 38.677249 | N33: Weigh bridge delays
D34: Luyaga Isaac | E34: 38.670139 | G34: Sentongo paul | I34: 42.469136 | J34: 34.126984 | L34: 38.819444
D35: Eriku Alipa | E35: 38.677249 | G35: Kyakulaga James | I35: 42.438973 | J35: 33.131614 | L35: 38.819444
D36: Sentongo paul | E36: 38.819444 | G36: SENTONG DAVID | H36: 46.284722 | I36: 42.386188 | J36: 34.47601 | K36: 32.59838 | L36: 38.819444
D37: Kyakulaga James | E37: 38.819444 | G37: Tumusiime Robert | H37: 40.3125 | I37: 42.800926 | J37: 40.3125 | K37: 36.402116 | L37: 38.819444
D38: SENTONG DAVID | E38: 38.819444 | G38: Kabanda Ronald | I38: 42.676505 | J38: 34.695767 | L38: 38.95216
D39: Tumusiime Robert | E39: 38.819444 | G39: Konge Husein | H39: 43.796296 | I39: 42.800926 | K39: 35.335648 | L39: 39.090909
D40: Kabanda Ronald | E40: 38.95216 | G40: Ngobi Fred | I40: 43.920718 | J40: 31.851852 | L40: 39.278846
D41: Konge Husein | E41: 39.090909 | G41: Isaac Tumuhimbise | H41: 44.238683 | I41: 42.800926 | J41: 34.506173 | K41: 35.252701 | L41: 39.693428
D42: Ngobi Fred | E42: 39.278846 | G42: Godwin Niwensiima | H42: 39.814815 | L42: 39.814815
D43: Isaac Tumuhimbise | E43: 39.693428 | G43: NAMINYA SIRAJE | H43: 39.814815 | L43: 39.814815
D44: NAMINYA SIRAJE | E44: 39.814815 | G44: Kakembo Masuud | H44: 40.212963 | L44: 40.212963
D45: Godwin Niwensiima | E45: 39.814815 | G45: James Kironde | H45: 45.189815 | I45: 43.022119 | J45: 33.842593 | K45: 37.326389 | L45: 40.519869
D46: Taimwa Alex | E46: 40.063657 | G46: Ntende Nassar | H46: 40.810185 | L46: 40.810185
D47: Kakembo Masuud | E47: 40.212963 | G47: Benon Ssempijja | H47: 48.524306 | I47: 44.179131 | J47: 28.368056 | K47: 35.61214 | L47: 40.916832
D48: James Kironde | E48: 40.519869 | G48: Hamudi Sesanga | H48: 41.363169 | L48: 41.363169
D49: Ntende Nassar | E49: 40.810185 | G49: Angello Lumala | H49: 42.203704 | L49: 42.203704
D50: Benon Ssempijja | E50: 40.916832 | G50: Bulega Sperito | H50: 42.303241 | L50: 42.303241
D51: Hamudi Sesanga | E51: 41.363169 | G51: Jacob Oneka | H51: 52.256944 | I51: 42.925347 | J51: 44.791667 | K51: 32.050926 | L51: 43.253367
D52: ALIPA EREKU | E52: 41.606481 | G52: KASULE JOHNBOSC | H52: 43.796296 | L52: 43.796296
D53: Angello Lumala | E53: 42.203704 | G53: SULAIMAN MUBIRU | H53: 46.782407 | L53: 46.782407
D54: Bulega Sperito | E54: 42.303241 | G54: BYEKWASO TWAHA | H54: 47.777778 | L54: 47.777778
D55: Jacob Oneka | E55: 43.253367 | G55: Ekwalikwa Yusuf | H55: 47.919974 | L55: 47.919974
D56: KASULE JOHNBOSC | E56: 43.796296 | G56: NASASIRA STEPHENE | H56: 49.768519 | L56: 49.768519
D57: SULAIMAN MUBIRU | E57: 46.782407 | G57: Grand Total | H57: 44.049089 | I57: 42.713613 | J57: 30.219944 | K57: 32.332375 | L57: 37.602537
D58: BYEKWASO TWAHA | E58: 47.777778
D59: Ekwalikwa Yusuf | E59: 47.919974
D60: NASASIRA STEPHENE | E60: 49.768519
D61: Grand Total | E61: 37.83724

Sheet Sheet6
B3: Column Labels
B4: January | C4: February | D4: March | E4: April | F4: May | G4: (blank) | H4: Grand Total
A5: Average of AVE Departure | B5: 43.986135 | C5: 42.703066 | D5: 30.284293 | E5: 31.940911 | F5: 31.362066 | H5: 36.065286

Sheet Sheet7
B3: Column Labels
B4: January | C4: February | D4: March | E4: April | F4: May | G4: (blank) | H4: Grand Total
A5: Average of AVE Arrival Time | B5: 55.873067 | C5: 55.160639 | D5: 50.415357 | E5: 43.227632 | F5: 42.146908 | H5: 49.886548

Sheet 2025
A3: Row Labels | B3: Average of AVE Departure | E3: Count of Comment AVE Departure | F3: Column Labels | W3: Row Labels | X3: Average of AVE Arrival Time | Z3: Count of Comment AVE Arrival Time | AA3: Column Labels
A4: January | B4: 43.986135 | E4: Row Labels | F4: Damaged stock replacement | G4: DJ failures | H4: Driver delays | I4: found another truck waiting to be cleared at the gate | J4: Jam at the weigh bridge | K4: Meeting Delays | L4: network failures | M4: pressure balancing | N4: Pre-Trip inspection defect closure | O4: Reconciling stock count delays | P4: stock recon delays | Q4: Unplanned Training | R4: Water top up | S4: (blank) | T4: Grand Total | W4: January | X4: 55.873067 | Z4: Row Labels | AA4: beer topup delays | AB4: dj completion delays | AC4: dj failures | AD4: dj failures at the gate | AE4: empties confirmation delays | AF4: Failed batteries at the gate | AG4: Fork Lift Breakdown | AH4: found another truck at the gate | AI4: found another truck waiting to offload | AJ4: fuel delays | AK4: fueling delays | AL4: loading delays | AM4: offloading delays | AN4: pre trip inspections | AO4: sorting delays | AP4: Traffic at gate | AQ4: Grand Total
A5: February | B5: 42.703066 | E5: January | F5: 1 | G5: 9 | H5: 1 | J5: 7 | K5: 2 | N5: 3 | O5: 3 | Q5: 3 | T5: 29 | W5: February | X5: 55.160639 | Z5: January | AD5: 2 | AH5: 1 | AJ5: 1 | AL5: 1 | AO5: 1 | AP5: 2 | AQ5: 8
A6: March | B6: 30.284293 | E6: February | G6: 1 | N6: 2 | T6: 3 | W6: March | X6: 50.415357 | Z6: February | AD6: 4 | AF6: 1 | AK6: 8 | AN6: 7 | AO6: 3 | AQ6: 23
A7: April | B7: 31.940911 | E7: March | G7: 3 | I7: 2 | J7: 1 | L7: 2 | M7: 8 | N7: 2 | P7: 4 | R7: 1 | T7: 23 | W7: April | X7: 43.227632 | Z7: March | AA7: 1 | AB7: 1 | AC7: 1 | AD7: 8 | AE7: 1 | AF7: 3 | AG7: 1 | AI7: 1 | AK7: 6 | AM7: 4 | AN7: 3 | AO7: 10 | AQ7: 40
A8: May | B8: 31.362066 | E8: April | G8: 8 | I8: 6 | J8: 6 | L8: 8 | M8: 18 | N8: 5 | P8: 5 | R8: 6 | T8: 62 | W8: May | X8: 42.146908 | Z8: April | AA8: 4 | AD8: 3 | AE8: 3 | AF8: 4 | AG8: 5 | AI8: 17 | AK8: 9 | AM8: 5 | AO8: 7 | AQ8: 57
A9: (blank) | E9: May | G9: 18 | I9: 9 | J9: 4 | L9: 7 | M9: 12 | N9: 4 | P9: 6 | R9: 10 | T9: 70 | W9: (blank) | Z9: May | AA9: 3 | AB9: 1 | AD9: 3 | AF9: 2 | AG9: 1 | AI9: 16 | AK9: 3 | AM9: 2 | AN9: 1 | AO9: 6 | AQ9: 38
A10: Grand Total | B10: 36.065286 | E10: (blank) | P10: 1 | T10: 1 | W10: Grand Total | X10: 49.886548 | Z10: Grand Total | AA10: 8 | AB10: 2 | AC10: 1 | AD10: 20 | AE10: 4 | AF10: 10 | AG10: 7 | AH10: 1 | AI10: 34 | AJ10: 1 | AK10: 26 | AL10: 1 | AM10: 11 | AN10: 11 | AO10: 27 | AP10: 2 | AQ10: 166
E11: Grand Total | F11: 1 | G11: 39 | H11: 1 | I11: 17 | J11: 18 | K11: 2 | L11: 17 | M11: 38 | N11: 16 | O11: 3 | P11: 16 | Q11: 3 | R11: 17 | T11: 188

Sheet DATA SOURCE
A1: Create Date | B1: Month Name | C1: Transporter | D1: Load Number | E1: Mode Of Capture | F1: Driver Name | G1: Truck Number | H1: Customer Name | I1: Vol Hl | J1: InvoiceNumber | K1: MWarehouse | L1: Budgeted KMs | M1: Actual KM | N1: KM Deviation | O1: Comment | P1: Clock in | Q1: Planned Departure Time | R1: DJ Departure Time | S1: Depature Deviation (min) | T1: AVE Departure | U1: Comment AVE Departure | V1: Arrival At Customer | W1: Departure Time from Customer | X1: Service Time At Customer | Y1: Comment TAT | Z1: Arrival At Depot | AA1: Clock Out | AB1: AVE Arrival Time | AC1: Comment AVE Arrival Time | AD1: Actual Days in Route | AE1: Bud Days in Route | AF1: Days in Rout Deviation | AG1: Total Hour Route | AH1: Driver Rest Hours In Route | AI1: Total WH | AJ1: TLP | AK1: D1 | AL1: D2 | AM1: D3 | AN1: D4 | AO1: Comment Ave TIR
A2: 45658 | B2: =TEXT(A2, "MMMM") -> January | D2: OM02L6Y5 | E2: Manual | F2: MUKOSE MUZAMIRU | G2: UBE 690K | H2: Kato Investment Ltd -Kagadi | I2: 151.68 | J2: A19778 | K2: OM | L2: 670 | M2: 612 | N2: -5 | P2: =R2-TIME(0,40,0) -> 45658.332 | Q2: 45658.312 | R2: 45658.36 | S2: =(R2-Q2)*86000/60 -> 67.685185 | T2: =(R2-P2)*86000/60 -> 39.814815 | V2: 45659.422 | W2: 45659.574 | X2: =(W2-V2)*84600/60 -> 214.4375 | Y2: space consquents | Z2: 45660.432 | AA2: =Z2+TIME(0,59,0) -> 45660.473 | AB2: =(AA2-Z2)*84600/60 -> 57.770833 | AD2: =Z2-R2 -> 2.0725833 | AE2: 2 | AF2: =AE2-AD2 -> -0.072583333 | AG2: =AD2*24 -> 49.742 | AH2: =AG2-AI2 -> 24 | AI2: =((Z2 - R2) * 24) - (INT(Z2 - R2) * 12) -> 25.742 | AJ2: =I2/AI2 -> 5.8923161
A3: 45658.846 | B3: =TEXT(A3, "MMMM") -> January | D3: OM7APO5RR | E3: DJ | F3: Stephen Musoke | G3: UBJ 375N | H3: Kabaco U Ltd-Mbarara | I3: 140.1 | J3: Z82022 | K3: OM | L3: 20 | M3: 14 | N3: 3 | P3: =R3-TIME(0,43,0) -> 45659.622 | Q3: 45659.321 | R3: 45659.651 | S3: =(R3-Q3)*86000/60 -> 473.7963 | T3: =(R3-P3)*86000/60 -> 42.800926 | V3: 45659.672 | W3: 45659.806 | X3: =(W3-V3)*84600/60 -> 189.95833 | Y3: Reached late and offloaded the next day | Z3: 45659.84 | AA3: 45659.879 | AB3: =(AA3-Z3)*84600/60 -> 54.833333 | AD3: =Z3-R3 -> 0.18888889 | AE3: 1 | AF3: =AE3-AD3 -> 0.81111111 | AG3: =AD3*24 -> 4.5333333 | AH3: =AG3-AI3 -> 0 | AI3: =((Z3 - R3) * 24) - (INT(Z3 - R3) * 12) -> 4.5333333 | AJ3: =I3/AI3 -> 30.904412
A4: 45658.846 | B4: =TEXT(A4, "MMMM") -> January | D4: OMCOX6YRR | E4: DJ | F4: Isaac Tumuhimbise | G4: UBE 287X | H4: Kabaco U Ltd-Mbarara | I4: 153.6 | J4: Z82023 | K4: OM | L4: 20 | M4: 13 | N4: =M4-L4 -> -7 | P4: =R4-TIME(0,37,0) -> 45659.449 | Q4: 45659.321 | R4: 45659.475 | S4: =(R4-Q4)*86000/60 -> 220.97222 | T4: =(R4-P4)*86000/60 -> 36.828704 | V4: 45659.501 | W4: 45659.694 | X4: =(W4-V4)*84600/60 -> 272.20833 | Y4: truck faulty | Z4: 45659.72 | AA4: 45659.761 | AB4: =(AA4-Z4)*84600/60 -> 57.770833 | AD4: =Z4-R4 -> 0.24513889 | AE4: 1 | AF4: =AE4-AD4 -> 0.75486111 | AG4: =AD4*24 -> 5.8833333 | AH4: =AG4-AI4 -> 0 | AI4: =((Z4 - R4) * 24) - (INT(Z4 - R4) * 12) -> 5.8833333 | AJ4: =I4/AI4 -> 26.107649
A5: 45658.847 | B5: =TEXT(A5, "MMMM") -> January | D5: OMZLGL1RR | E5: DJ | F5: James Kironde | G5: UBK 881R | H5: KATO INVESTMENTS LIMITED-MASAK | I5: 153.6 | J5: F15655 | K5: OM | L5: 340 | M5: =L5+2 -> 342 | N5: =M5-L5 -> 2 | P5: 45659.291 | Q5: 45659.176 | R5: 45659.317 | S5: =(R5-Q5)*86000/60 -> 202.06019 | T5: =(R5-P5)*86000/60 -> 37.824074 | V5: 45659.392 | W5: 45659.566 | X5: =(W5-V5)*84600/60 -> 245.77083 | Y5: slept at the RD and offloaded the next day | Z5: 45660.39 | AA5: =Z5+TIME(0,59,0) -> 45660.431 | AB5: =(AA5-Z5)*84600/60 -> 57.770833 | AD5: =Z5-R5 -> 1.0729167 | AE5: 1 | AF5: =AE5-AD5 -> -0.072916667 | AG5: =AD5*24 -> 25.75 | AH5: =AG5-AI5 -> 12 | AI5: =((Z5 - R5) * 24) - (INT(Z5 - R5) * 12) -> 13.75 | AJ5: =I5/AI5 -> 11.170909
A6: 45658.848 | B6: =TEXT(A6, "MMMM") -> January | D6: OM33KZQRR | E6: DJ | F6: Jacob Oneka | G6: UBE 422T | H6: Kato Investments Ltd-Bulenga | I6: 153.6 | J6: A19779 | K6: OM | L6: 560 | M6: =L6-1 -> 559 | N6: =M6-L6 -> -1 | P6: =R6-TIME(0,65,0) -> 45659.487 | Q6: 45658.896 | R6: 45659.533 | S6: =(R6-Q6)*86000/60 -> 912.75463 | T6: =(R6-P6)*86000/60 -> 64.699074 | U6: DJ failures | V6: 45660.448 | W6: 45660.649 | X6: =(W6-V6)*84600/60 -> 283.95833 | Y6: Waited for empties from trade | Z6: 45661.486 | AA6: =Z6+TIME(0,54,0) -> 45661.524 | AB6: =(AA6-Z6)*84600/60 -> 52.875 | AD6: =Z6-R6 -> 1.9534722 | AE6: 2 | AF6: =AE6-AD6 -> 0.046527778 | AG6: =AD6*24 -> 46.883333 | AH6: =AG6-AI6 -> 12 | AI6: =((Z6 - R6) * 24) - (INT(Z6 - R6) * 12) -> 34.883333 | AJ6: =I6/AI6 -> 4.4032489
A7: 45658.849 | B7: =TEXT(A7, "MMMM") -> January | D7: OMCP7C6RR | E7: Manual | F7: Kilabila Ismail | G7: UBE 419T | H7: RUGOMA TRADERS CO. LTD NTUNGAM | I7: 153.6 | J7: F15657 | K7: OM | L7: 130 | M7: =L7-1 -> 129 | N7: =M7-L7 -> -1 | P7: =R7-TIME(0,77,0) -> 45659.343 | Q7: 45659.349 | R7: 45659.396 | S7: =(R7-Q7)*86000/60 -> 67.685185 | T7: =(R7-P7)*86000/60 -> 76.643519 | U7: Jam at the weigh bridge | V7: 45659.5 | W7: 45659.709 | X7: =(W7-V7)*84600/60 -> 293.75 | Y7: Waited for empties from trade | Z7: 45659.799 | AA7: 45659.838 | AB7: =(AA7-Z7)*84600/60 -> 54.833333 | AD7: =Z7-R7 -> 0.40277778 | AE7: 1 | AF7: =AE7-AD7 -> 0.59722222 | AG7: =AD7*24 -> 9.6666667 | AH7: =AG7-AI7 -> 0 | AI7: =((Z7 - R7) * 24) - (INT(Z7 - R7) * 12) -> 9.6666667 | AJ7: =I7/AI7 -> 15.889655
A8: 45658.853 | B8: =TEXT(A8, "MMMM") -> January | D8: OMO39VURR | E8: DJ | F8: ALIPA EREKU | G8: UBK 858R | H8: KATO INVESTMENTS LTD-KATIKARA | I8: 133.44 | J8: A19781 | K8: OM | L8: 790 | M8: =L8+2 -> 792 | N8: =M8-L8 -> 2 | P8: =R8-TIME(0,40,0) -> 45658.844 | Q8: 45659.658 | R8: 45658.872 | S8: =(R8-Q8)*86000/60 -> -1126.7593 | T8: =(R8-P8)*86000/60 -> 39.814815 | V8: 45660.332 | W8: 45660.511 | X8: =(W8-V8)*84600/60 -> 252.625 | Y8: found another truck at the RD and offloaded the next day | Z8: 45661.477 | AA8: =Z8+TIME(0,59,0) -> 45661.518 | AB8: =(AA8-Z8)*84600/60 -> 57.770833 | AD8: =Z8-R8 -> 2.6048611 | AE8: 3 | AF8: =AE8-AD8 -> 0.39513889 | AG8: =AD8*24 -> 62.516667 | AH8: =AG8-AI8 -> 24 | AI8: =((Z8 - R8) * 24) - (INT(Z8 - R8) * 12) -> 38.516667 | AJ8: =I8/AI8 -> 3.4644743
A9: 45659.74 | B9: =TEXT(A9, "MMMM") -> January | D9: OMY25R8RR | E9: DJ | F9: Benon Ssempijja | G9: UAY 526V | H9: Ntale and Sons | I9: 153.6 | J9: A19789 | K9: OM | L9: 810 | M9: =L9+2 -> 812 | N9: =M9-L9 -> 2 | P9: =R9-TIME(0,39,0) -> 45660.321 | Q9: 45659.812 | R9: 45660.348 | S9: =(R9-Q9)*86000/60 -> 767.43056 | T9: =(R9-P9)*86000/60 -> 38.819444 | V9: 45660.866 | W9: 45661.583 | X9: =(W9-V9)*84600/60 -> 1010.5 | Y9: Waited for empties from trade | Z9: 45662.633 | AA9: 45662.667 | AB9: =(AA9-Z9)*84600/60 -> 47.979167 | AD9: =Z9-R9 -> 2.2847222 | AE9: 3 | AF9: =AE9-AD9 -> 0.71527778 | AG9: =AD9*24 -> 54.833333 | AH9: =AG9-AI9 -> 24 | AI9: =((Z9 - R9) * 24) - (INT(Z9 - R9) * 12) -> 30.833333 | AJ9: =I9/AI9 -> 4.9816216
A10: 45659.74 | B10: =TEXT(A10, "MMMM") -> January | D10: OM84GFKRR | E10: DJ | F10: Kilabila Ismail | G10: UBE 419T | H10: KATO INVESTMENTS LIMITED-MASAK | I10: 153.6 | J10: F15658 | K10: OM | L10: 340 | M10: 340 | N10: =M10-L10 -> 0 | P10: =R10-TIME(0,43,0) -> 45659.751 | Q10: 45660.176 | R10: 45659.781 | S10: =(R10-Q10)*86000/60 -> -567.36111 | T10: =(R10-P10)*86000/60 -> 42.800926 | V10: 45660.506 | W10: 45660.631 | X10: =(W10-V10)*84600/60 -> 176.25 | Z10: 45661.444 | AA10: 45661.483 | AB10: =(AA10-Z10)*84600/60 -> 54.833333 | AD10: =Z10-R10 -> 1.6638889 | AE10: 2 | AF10: =AE10-AD10 -> 0.33611111 | AG10: =AD10*24 -> 39.933333 | AH10: =AG10-AI10 -> 12 | AI10: =((Z10 - R10) * 24) - (INT(Z10 - R10) * 12) -> 27.933333 | AJ10: =I10/AI10 -> 5.4988067
A11: 45659.967 | B11: =TEXT(A11, "MMMM") -> January | D11: OMN00PNRR | E11: DJ | F11: James Kironde | G11: UBK 881R | H11: Sawan Distributors Ltd-Nabingo | I11: 153.6 | J11: A19800 | K11: OM | L11: 560 | M11: =L11+2 -> 562 | N11: =M11-L11 -> 2 | P11: =R11-TIME(0,59,0) -> 45660.562 | Q11: 45660.333 | R11: 45660.603 | S11: =(R11-Q11)*86000/60 -> 387.19907 | T11: =(R11-P11)*86000/60 -> 58.726852 | U11: DJ failures | V11: 45660.881 | W11: 45661.524 | X11: =(W11-V11)*84600/60 -> 906.70833 | Y11: space consquents | Z11: 45663.591 | AA11: =Z11+TIME(0,59,0) -> 45663.632 | AB11: =(AA11-Z11)*84600/60 -> 57.770833 | AD11: =Z11-R11 -> 2.9875 | AE11: 2 | AF11: =AE11-AD11 -> -0.9875 | AG11: =AD11*24 -> 71.7 | AH11: =AG11-AI11 -> 24 | AI11: =((Z11 - R11) * 24) - (INT(Z11 - R11) * 12) -> 47.7 | AJ11: =I11/AI11 -> 3.2201258
A12: 45659.968 | B12: =TEXT(A12, "MMMM") -> January | D12: OM8F9LXRR | E12: DJ | F12: Bisaso Ronald | G12: UBK 875R | H12: Kabaco U Ltd-Mbarara | I12: 149.4 | J12: Z82038 | K12: OM | L12: 20 | M12: =L12+2 -> 22 | N12: =M12-L12 -> 2 | P12: 45660.583 | Q12: 45660.333 | R12: 45660.609 | S12: =(R12-Q12)*86000/60 -> 395.16204 | T12: =(R12-P12)*86000/60 -> 37.824074 | V12: 45660.658 | W12: 45660.782 | X12: =(W12-V12)*84600/60 -> 175.27083 | Z12: 45660.803 | AA12: 45660.839 | AB12: =(AA12-Z12)*84600/60 -> 50.916667 | AD12: =Z12-R12 -> 0.19375 | AE12: 2 | AF12: =AE12-AD12 -> 1.80625 | AG12: =AD12*24 -> 4.65 | AH12: =AG12-AI12 -> 0 | AI12: =((Z12 - R12) * 24) - (INT(Z12 - R12) * 12) -> 4.65 | AJ12: =I12/AI12 -> 32.129032
A13: 45659.969 | B13: =TEXT(A13, "MMMM") -> January | D13: OMHX7MPRR | E13: DJ | F13: Stephen Musoke | G13: UBJ 375N | H13: Kobusinge Steven-Kamwenge | I13: 153.6 | J13: Z82039 | K13: OM | L13: 230 | M13: 230 | N13: =M13-L13 -> 0 | P13: 45660.383 | Q13: 45660.375 | R13: 45660.413 | S13: =(R13-Q13)*86000/60 -> 54.74537 | T13: =(R13-P13)*86000/60 -> 43.796296 | V13: 45660.549 | W13: 45660.714 | X13: =(W13-V13)*84600/60 -> 233.04167 | Y13: Waited for empties from trade | Z13: 45661.398 | AA13: =Z13+TIME(0,59,0) -> 45661.439 | AB13: =(AA13-Z13)*84600/60 -> 57.770833 | AD13: =Z13-R13 -> 0.98472222 | AE13: 2 | AF13: =AE13-AD13 -> 1.0152778 | AG13: =AD13*24 -> 23.633333 | AH13: =AG13-AI13 -> 0 | AI13: =((Z13 - R13) * 24) - (INT(Z13 - R13) * 12) -> 23.633333 | AJ13: =I13/AI13 -> 6.4992948
A14: 45659.969 | B14: =TEXT(A14, "MMMM") -> January | D14: OMVZ7HGRR | E14: DJ | F14: Isaac Tumuhimbise | G14: UBE 287X | H14: Agaba Services | I14: 153.6 | J14: F15659 | K14: OM | L14: 302 | M14: 293 | N14: =M14-L14 -> -9 | P14: =R14-TIME(0,57,0) -> 45660.262 | Q14: 45660.354 | R14: 45660.301 | S14: =(R14-Q14)*86000/60 -> -75.648148 | T14: =(R14-P14)*86000/60 -> 56.736111 | U14: Meeting Delays | V14: 45660.526 | W14: 45660.607 | X14: =(W14-V14)*84600/60 -> 114.5625 | Z14: 45661.358 | AA14: 45661.394 | AB14: =(AA14-Z14)*84600/60 -> 50.916667 | AD14: =Z14-R14 -> 1.0569444 | AE14: 2 | AF14: =AE14-AD14 -> 0.94305556 | AG14: =AD14*24 -> 25.366667 | AH14: =AG14-AI14 -> 12 | AI14: =((Z14 - R14) * 24) - (INT(Z14 - R14) * 12) -> 13.366667 | AJ14: =I14/AI14 -> 11.491272
A15: 45659.97 | B15: =TEXT(A15, "MMMM") -> January | D15: OM976EURR | E15: DJ | F15: Mugisha George | G15: UAV 203T | H15: Kobusinge Acaali- Kyenjojo | I15: 153.6 | J15: Z82040 | K15: OM | L15: 480 | M15: 469 | N15: =M15-L15 -> -11 | P15: =R15-TIME(0,76,0) -> 45660.37 | Q15: 45661.137 | R15: 45660.423 | S15: =(R15-Q15)*86000/60 -> -1023.2407 | T15: =(R15-P15)*86000/60 -> 75.648148 | U15: Damaged stock replacement | V15: 45661.351 | W15: 45661.568 | X15: =(W15-V15)*84600/60 -> 305.5 | Y15: Waited for empties from trade | Z15: 45662.418 | AA15: =Z15+TIME(0,57,0) -> 45662.458 | AB15: =(AA15-Z15)*84600/60 -> 55.8125 | AD15: =Z15-R15 -> 1.9951389 | AE15: 2 | AF15: =AE15-AD15 -> 0.0048611111 | AG15: =AD15*24 -> 47.883333 | AH15: =AG15-AI15 -> 12 | AI15: =((Z15 - R15) * 24) - (INT(Z15 - R15) * 12) -> 35.883333 | AJ15: =I15/AI15 -> 4.2805388
A16: 45660 | B16: =TEXT(A16, "MMMM") -> January | D16: OM02L7BP | E16: Manual | G16: UBE 678K | H16: Ntale and Sons Ltd-Kakiri | I16: 156 | J16: A19821 | K16: OM | L16: 620 | M16: 612 | N16: =M16-L16 -> -8 | P16: =R16-TIME(0,40,0) -> 45660.337 | Q16: 45660.312 | R16: 45660.365 | S16: =(R16-Q16)*86000/60 -> 74.652778 | T16: =(R16-P16)*86000/60 -> 39.814815 | V16: 45660.885 | W16: =V16+TIME(0,367,0) -> 45661.14 | X16: =(W16-V16)*84600/60 -> 359.35417 | Y16: Waited for empties from trade | Z16: 45662.595 | AA16: =Z16+TIME(0,57,0) -> 45662.635 | AB16: =(AA16-Z16)*84600/60 -> 55.8125 | AD16: =Z16-R16 -> 2.2308333 | AE16: 3 | AF16: =AE16-AD16 -> 0.76916667 | AG16: =AD16*24 -> 53.54 | AH16: =AG16-AI16 -> 24 | AI16: =((Z16 - R16) * 24) - (INT(Z16 - R16) * 12) -> 29.54 | AJ16: =I16/AI16 -> 5.2809749
A17: 45660 | B17: =TEXT(A17, "MMMM") -> January | D17: OM02L7BK | E17: Manual | G17: UBE 678K | H17: Kato Investments Ltd- Kakumiro | I17: 156 | J17: A19818 | K17: OM | L17: 765 | M17: =L17+2 -> 767 | N17: =M17-L17 -> 2 | P17: =R17-TIME(0,41,0) -> 45660.342 | Q17: 45660.312 | R17: 45660.37 | S17: =(R17-Q17)*86000/60 -> 82.615741 | T17: =(R17-P17)*86000/60 -> 40.810185 | V17: 45660.745 | W17: =V17+TIME(0,153,0) -> 45660.851 | X17: =(W17-V17)*84600/60 -> 149.8125 | Z17: 45661.88 | AA17: =Z17+TIME(0,59,0) -> 45661.921 | AB17: =(AA17-Z17)*84600/60 -> 57.770833 | AD17: =Z17-R17 -> 1.5101667 | AE17: 3 | AF17: =AE17-AD17 -> 1.4898333 | AG17: =AD17*24 -> 36.244 | AH17: =AG17-AI17 -> 12 | AI17: =((Z17 - R17) * 24) - (INT(Z17 - R17) * 12) -> 24.244 | AJ17: =I17/AI17 -> 6.4345818
A18: 45660 | B18: =TEXT(A18, "MMMM") -> January | D18: OM02L7BR | E18: Manual | F18: MUKOSE MUZAMIRU | G18: UBE 690K | H18: Kabaco U Ltd | I18: 156 | J18: Z82048 | K18: OM | L18: 320 | M18: 319 | N18: =M18-L18 -> -1 | P18: =R18-TIME(0,43,0) -> 45660.333 | Q18: 45660.312 | R18: 45660.362 | S18: =(R18-Q18)*86000/60 -> 71.666667 | T18: =(R18-P18)*86000/60 -> 42.800926 | V18: 45660.612 | W18: =V18+TIME(0,161,0) -> 45660.724 | X18: =(W18-V18)*84600/60 -> 157.64583 | Z18: 45661.492 | AA18: 45661.533 | AB18: =(AA18-Z18)*84600/60 -> 57.770833 | AD18: =Z18-R18 -> 1.1293056 | AE18: 2 | AF18: =AE18-AD18 -> 0.87069444 | AG18: =AD18*24 -> 27.103333 | AH18: =AG18-AI18 -> 12 | AI18: =((Z18 - R18) * 24) - (INT(Z18 - R18) * 12) -> 15.103333 | AJ18: =I18/AI18 -> 10.328846
A19: 45660 | B19: =TEXT(A19, "MMMM") -> January | D19: OM02L777 | E19: Manual | G19: UBP 311H | H19: Kato Investments Ltd- Kyegegwa | I19: 156 | J19: A19812 | K19: OM | L19: 600 | M19: 591 | N19: =M19-L19 -> -9 | P19: =R19-TIME(0,77,0) -> 45660.312 | Q19: 45660.312 | R19: 45660.365 | S19: =(R19-Q19)*86000/60 -> 75.648148 | T19: =(R19-P19)*86000/60 -> 76.643519 | U19: Pre-Trip inspection defect closure | V19: 45661.462 | W19: =V19+TIME(0,175,0) -> 45661.584 | X19: =(W19-V19)*84600/60 -> 171.35417 | Z19: 45661.886 | AA19: =Z19+TIME(0,56,0) -> 45661.925 | AB19: =(AA19-Z19)*84600/60 -> 54.833333 | AD19: =Z19-R19 -> 1.5208333 | AE19: 2 | AF19: =AE19-AD19 -> 0.47916667 | AG19: =AD19*24 -> 36.5 | AH19: =AG19-AI19 -> 12 | AI19: =((Z19 - R19) * 24) - (INT(Z19 - R19) * 12) -> 24.5 | AJ19: =I19/AI19 -> 6.3673469
A20: 45660 | B20: =TEXT(A20, "MMMM") -> January | D20: OM02L77A | E20: Manual | G20: UBP 311H | H20: Kobusinge Steven-FPortal | I20: 156 | J20: Z82042 | K20: OM | L20: 390 | M20: 386 | N20: =M20-L20 -> -4 | P20: =R20-TIME(0,43,0) -> 45660.336 | Q20: 45660.312 | R20: 45660.366 | S20: =(R20-Q20)*86000/60 -> 76.643519 | T20: =(R20-P20)*86000/60 -> 42.800926 | V20: 45661.428 | W20: =V20+TIME(0,153,0) -> 45661.535 | X20: =(W20-V20)*84600/60 -> 149.8125 | Z20: 45662.372 | AA20: =Z20+TIME(0,59,0) -> 45662.413 | AB20: =(AA20-Z20)*84600/60 -> 57.770833 | AD20: =Z20-R20 -> 2.0065 | AE20: 2 | AF20: =AE20-AD20 -> -0.0065 | AG20: =AD20*24 -> 48.156 | AH20: =AG20-AI20 -> 24 | AI20: =((Z20 - R20) * 24) - (INT(Z20 - R20) * 12) -> 24.156 | AJ20: =I20/AI20 -> 6.4580229
A21: 45660 | B21: =TEXT(A21, "MMMM") -> January | D21: OM02L7BL | E21: Manual | F21: Ekwalikwa Yusuf | G21: UBP 311H | H21: Kobusinge Steven-Kamwenge | I21: 156 | J21: Z82047 | K21: OM | L21: 230 | M21: =L21+2 -> 232 | N21: =M21-L21 -> 2 | P21: =R21-TIME(0,39,0) -> 45660.349 | Q21: 45660.312 | R21: 45660.376 | S21: =(R21-Q21)*86000/60 -> 91.574074 | T21: =(R21-P21)*86000/60 -> 38.819444 | V21: 45661.397 | W21: =V21+TIME(0,149,0) -> 45661.501 | X21: =(W21-V21)*84600/60 -> 145.89583 | Z21: 45661.822 | AA21: =Z21+TIME(0,52,0) -> 45661.858 | AB21: =(AA21-Z21)*84600/60 -> 50.916667 | AD21: =Z21-R21 -> 1.4451389 | AE21: 2 | AF21: =AE21-AD21 -> 0.55486111 | AG21: =AD21*24 -> 34.683333 | AH21: =AG21-AI21 -> 12 | AI21: =((Z21 - R21) * 24) - (INT(Z21 - R21) * 12) -> 22.683333 | AJ21: =I21/AI21 -> 6.8772961
A22: 45660 | B22: =TEXT(A22, "MMMM") -> January | D22: OM02L7BM | E22: Manual | F22: Ekwalikwa Yusuf | G22: UBP 311H | H22: Kato Investment Ltd -Mubende | I22: 154.344 | J22: A19820 | K22: OM | L22: 680 | M22: =L22+2 -> 682 | N22: =M22-L22 -> 2 | P22: =R22-TIME(0,43,0) -> 45660.344 | Q22: 45660.312 | R22: 45660.374 | S22: =(R22-Q22)*86000/60 -> 87.592593 | T22: =(R22-P22)*86000/60 -> 42.800926 | V22: 45661.469 | W22: =V22+TIME(0,175,0) -> 45661.59 | X22: =(W22-V22)*84600/60 -> 171.35417 | Z22: 45662.787 | AA22: 45662.819 | AB22: =(AA22-Z22)*84600/60 -> 46.020833 | AD22: =Z22-R22 -> 2.4130556 | AE22: 2 | AF22: =AE22-AD22 -> -0.41305556 | AG22: =AD22*24 -> 57.913333 | AH22: =AG22-AI22 -> 24 | AI22: =((Z22 - R22) * 24) - (INT(Z22 - R22) * 12) -> 33.913333 | AJ22: =I22/AI22 -> 4.5511303
A23: 45660 | B23: =TEXT(A23, "MMMM") -> January | D23: OM02L77B | E23: Manual | G23: UBP 311H | H23: KATO INVESTMENTS LTD-KATIKARA | I23: 156 | J23: A19813 | K23: OM | L23: 790 | M23: =L23+2 -> 792 | N23: =M23-L23 -> 2 | P23: 45660.332 | Q23: 45660.312 | R23: 45660.36 | S23: =(R23-Q23)*86000/60 -> 67.685185 | T23: =(R23-P23)*86000/60 -> 39.814815 | V23: 45661.412 | W23: =V23+TIME(0,336,0) -> 45661.645 | X23: =(W23-V23)*84600/60 -> 329 | Y23: found another truck to be offloaded | Z23: 45662.819 | AA23: 45662.86 | AB23: =(AA23-Z23)*84600/60 -> 57.770833 | AD23: =Z23-R23 -> 2.4597222 | AE23: 3 | AF23: =AE23-AD23 -> 0.54027778 | AG23: =AD23*24 -> 59.033333 | AH23: =AG23-AI23 -> 24 | AI23: =((Z23 - R23) * 24) - (INT(Z23 - R23) * 12) -> 35.033333 | AJ23: =I23/AI23 -> 4.452902
A24: 45660 | B24: =TEXT(A24, "MMMM") -> January | D24: OM02L7BH | E24: Manual | G24: UBP 311H | H24: Kobusinge Steven-FPortal | I24: 156 | J24: Z82046 | K24: OM | L24: 390 | M24: 386 | N24: =M24-L24 -> -4 | P24: =R24-TIME(0,63,0) -> 45660.316 | Q24: 45660.312 | R24: 45660.36 | S24: =(R24-Q24)*86000/60 -> 67.685185 | T24: =(R24-P24)*86000/60 -> 62.708333 | U24: Meeting Delays | V24: 45661.422 | W24: =V24+TIME(0,153,0) -> 45661.528 | X24: =(W24-V24)*84600/60 -> 149.8125 | Z24: 45662.396 | AA24: =Z24+TIME(0,57,0) -> 45662.436 | AB24: =(AA24-Z24)*84600/60 -> 55.8125 | AD24: =Z24-R24 -> 2.0365 | AE24: 2 | AF24: =AE24-AD24 -> -0.0365 | AG24: =AD24*24 -> 48.876 | AH24: =AG24-AI24 -> 24 | AI24: =((Z24 - R24) * 24) - (INT(Z24 - R24) * 12) -> 24.876 | AJ24: =I24/AI24 -> 6.2711047
A25: 45660.501 | B25: =TEXT(A25, "MMMM") -> January | D25: OMJVKLYRR | E25: DJ | F25: Abel Mark naffa | G25: UBJ 415C | H25: KATO INVESTMENTS LIMITED-MASAK | I25: 153.6 | J25: F15660 | K25: OM | L25: 340 | M25: 255 | N25: =M25-L25 -> -85 | P25: =R25-TIME(0,35,0) -> 45660.68 | Q25: 45661.176 | R25: 45660.704 | S25: =(R25-Q25)*86000/60 -> -676.85185 | T25: =(R25-P25)*86000/60 -> 34.837963 | V25: 45661.5 | W25: =V25+TIME(0,149,0) -> 45661.603 | X25: =(W25-V25)*84600/60 -> 145.89583 | Z25: 45663.544 | AA25: =Z25+TIME(0,59,0) -> 45663.585 | AB25: =(AA25-Z25)*84600/60 -> 57.770833 | AD25: =Z25-R25 -> 2.8395833 | AE25: 2 | AF25: =AE25-AD25 -> -0.83958333 | AG25: =AD25*24 -> 68.15 | AH25: =AG25-AI25 -> 24 | AI25: =((Z25 - R25) * 24) - (INT(Z25 - R25) * 12) -> 44.15 | AJ25: =I25/AI25 -> 3.4790487
A26: 45660.503 | B26: =TEXT(A26, "MMMM") -> January | D26: OMFII1DRR | E26: Manual | F26: Angello Lumala | G26: UAV 051U | H26: KATO INVESTMENTS LTD- KALISIZO | I26: 153.6 | J26: F15661 | K26: OM | L26: 350 | M26: 351 | N26: =M26-L26 -> 1 | P26: =R26-TIME(0,43,0) -> 45661.023 | Q26: 45661.003 | R26: 45661.053 | S26: =(R26-Q26)*86000/60 -> 71.666667 | T26: =(R26-P26)*86000/60 -> 42.800926 | V26: 45661.344 | W26: =V26+TIME(0,153,0) -> 45661.45 | X26: =(W26-V26)*84600/60 -> 149.8125 | Z26: 45661.761 | AA26: 45661.802 | AB26: =(AA26-Z26)*84600/60 -> 57.770833 | AD26: =Z26-R26 -> 0.70833333 | AE26: 2 | AF26: =AE26-AD26 -> 1.2916667 | AG26: =AD26*24 -> 17 | AH26: =AG26-AI26 -> 0 | AI26: =((Z26 - R26) * 24) - (INT(Z26 - R26) * 12) -> 17 | AJ26: =I26/AI26 -> 9.0352941
A27: 45660.505 | B27: =TEXT(A27, "MMMM") -> January | D27: OMY3M6PRR | E27: DJ | F27: Tumusiime Robert | G27: UBJ 988D | H27: RUGOMA TRADERS CO. LTD NTUNGAM | I27: 153.6 | J27: F15662 | K27: OM | L27: 130 | M27: =L27-1 -> 129 | N27: =M27-L27 -> -1 | P27: =R27-TIME(0,39,0) -> 45660.726 | Q27: 45661.26 | R27: 45660.753 | S27: =(R27-Q27)*86000/60 -> -727.61574 | T27: =(R27-P27)*86000/60 -> 38.819444 | V27: 45661.332 | W27: =V27+TIME(0,161,0) -> 45661.444 | X27: =(W27-V27)*84600/60 -> 157.64583 | Z27: 45661.714 | AA27: 45661.755 | AB27: =(AA27-Z27)*84600/60 -> 57.770833 | AD27: =Z27-R27 -> 0.96111111 | AE27: 1 | AF27: =AE27-AD27 -> 0.038888889 | AG27: =AD27*24 -> 23.066667 | AH27: =AG27-AI27 -> 0 | AI27: =((Z27 - R27) * 24) - (INT(Z27 - R27) * 12) -> 23.066667 | AJ27: =I27/AI27 -> 6.6589595
A28: 45660.506 | B28: =TEXT(A28, "MMMM") -> January | D28: OM0MCP3RR | E28: DJ | F28: SULAIMAN MUBIRU | G28: UBK 862R | H28: Boniface Harera | I28: 156 | J28: F15663 | K28: OM | L28: 470 | M28: =L28-1 -> 469 | N28: =M28-L28 -> -1 | P28: =R28-TIME(0,53,0) -> 45660.608 | Q28: 45661.062 | R28: 45660.644 | S28: =(R28-Q28)*86000/60 -> -599.21296 | T28: =(R28-P28)*86000/60 -> 52.75463 | U28: Jam at the weigh bridge | V28: 45661.431 | W28: =V28+TIME(0,175,0) -> 45661.553 | X28: =(W28-V28)*84600/60 -> 171.35417 | Z28: 45661.427 | AA28: =Z28+TIME(0,54,0) -> 45661.465 | AB28: =(AA28-Z28)*84600/60 -> 52.875 | AD28: =Z28-R28 -> 0.78263889 | AE28: 2 | AF28: =AE28-AD28 -> 1.2173611 | AG28: =AD28*24 -> 18.783333 | AH28: =AG28-AI28 -> 0 | AI28: =((Z28 - R28) * 24) - (INT(Z28 - R28) * 12) -> 18.783333 | AJ28: =I28/AI28 -> 8.3052351
A29: 45660.855 | B29: =TEXT(A29, "MMMM") -> January | D29: OMHN31TRR | E29: DJ | F29: Konge Husein | G29: UBJ 707D | H29: Kabaco U Ltd-Mbarara | I29: 151.8 | J29: Z82049 | K29: OM | L29: 20 | M29: 14 | N29: =M29-L29 -> -6 | P29: =R29-TIME(0,53,0) -> 45661.312 | Q29: 45661.321 | R29: 45661.349 | S29: =(R29-Q29)*86000/60 -> 39.814815 | T29: =(R29-P29)*86000/60 -> 52.75463 | U29: Jam at the weigh bridge | V29: 45661.384 | W29: =V29+TIME(0,320,0) -> 45661.606 | X29: =(W29-V29)*84600/60 -> 313.33333 | Y29: Waited for empties from trade | Z29: 45661.592 | AA29: 45661.624 | AB29: =(AA29-Z29)*84600/60 -> 46.020833 | AD29: =Z29-R29 -> 0.24305556 | AE29: 2 | AF29: =AE29-AD29 -> 1.7569444 | AG29: =AD29*24 -> 5.8333333 | AH29: =AG29-AI29 -> 0 | AI29: =((Z29 - R29) * 24) - (INT(Z29 - R29) * 12) -> 5.8333333 | AJ29: =I29/AI29 -> 26.022857
A30: 45660.86 | B30: =TEXT(A30, "MMMM") -> January | D30: OM4WLDZRR | E30: Manual | F30: Kabene John | G30: UBA 523T | H30: RUGOMA TRADERS CO. LTD NTUNGAM | I30: 153.6 | J30: F15664 | K30: OM | L30: 130 | M30: =L30-1 -> 129 | N30: =M30-L30 -> -1 | P30: =R30-TIME(0,43,0) -> 45661.377 | Q30: 45661.36 | R30: 45661.407 | S30: =(R30-Q30)*86000/60 -> 67.685185 | T30: =(R30-P30)*86000/60 -> 42.800926 | V30: 45661.502 | W30: =V30+TIME(0,167,0) -> 45661.618 | X30: =(W30-V30)*84600/60 -> 163.52083 | Z30: 45661.777 | AA30: =Z30+TIME(0,59,0) -> 45661.818 | AB30: =(AA30-Z30)*84600/60 -> 57.770833 | AD30: =Z30-R30 -> 0.36944444 | AE30: 1 | AF30: =AE30-AD30 -> 0.63055556 | AG30: =AD30*24 -> 8.8666667 | AH30: =AG30-AI30 -> 0 | AI30: =((Z30 - R30) * 24) - (INT(Z30 - R30) * 12) -> 8.8666667 | AJ30: =I30/AI30 -> 17.323308
A31: 45660.863 | B31: =TEXT(A31, "MMMM") -> January | D31: OMF1PUWRR | E31: DJ | F31: Bisaso Ronald | G31: UBK 875R | H31: Ntale and Sons | I31: 151.944 | J31: A19824 | K31: OM | L31: 810 | M31: =L31-1 -> 809 | N31: =M31-L31 -> -1 | P31: =R31-TIME(0,39,0) -> 45661.343 | Q31: 45660.896 | R31: 45661.37 | S31: =(R31-Q31)*86000/60 -> 679.83796 | T31: =(R31-P31)*86000/60 -> 38.819444 | V31: 45663.606 | W31: =V31+TIME(0,153,0) -> 45663.712 | X31: =(W31-V31)*84600/60 -> 149.8125 | Z31: 45664.862 | AA31: =Z31+TIME(0,59,0) -> 45664.903 | AB31: =(AA31-Z31)*84600/60 -> 57.770833 | AD31: =Z31-R31 -> 3.4916667 | AE31: 3 | AF31: =AE31-AD31 -> -0.49166667 | AG31: =AD31*24 -> 83.8 | AH31: =AG31-AI31 -> 36 | AI31: =((Z31 - R31) * 24) - (INT(Z31 - R31) * 12) -> 47.8 | AJ31: =I31/AI31 -> 3.1787448
A32: 45660.863 | B32: =TEXT(A32, "MMMM") -> January | D32: OM7HSU6RR | E32: DJ | F32: Isaac Tumuhimbise | G32: UBE 287X | H32: KATO INVESTMENTS LIMITED-MASAK | I32: 153.6 | J32: F15665 | K32: OM | L32: 340 | M32: 296 | N32: =M32-L32 -> -44 | P32: =R32-TIME(0,40,0) -> 45661.469 | Q32: 45661.176 | R32: 45661.497 | S32: =(R32-Q32)*86000/60 -> 459.86111 | T32: =(R32-P32)*86000/60 -> 39.814815 | V32: 45662.378 | W32: =V32+TIME(0,175,0) -> 45662.5 | X32: =(W32-V32)*84600/60 -> 171.35417 | Z32: 45662.665 | AA32: =Z32+TIME(0,57,0) -> 45662.705 | AB32: =(AA32-Z32)*84600/60 -> 55.8125 | AD32: =Z32-R32 -> 1.1680556 | AE32: 2 | AF32: =AE32-AD32 -> 0.83194444 | AG32: =AD32*24 -> 28.033333 | AH32: =AG32-AI32 -> 12 | AI32: =((Z32 - R32) * 24) - (INT(Z32 - R32) * 12) -> 16.033333 | AJ32: =I32/AI32 -> 9.5800416
A33: 45660.864 | B33: =TEXT(A33, "MMMM") -> January | D33: OMS5GYURR | E33: DJ | F33: NAMINYA SIRAJE | G33: UBP 301H | H33: Boniface Harera | I33: 156 | J33: F15666 | K33: OM | L33: 470 | M33: =L33-1 -> 469 | N33: =M33-L33 -> -1 | P33: =R33-TIME(0,40,0) -> 45660.81 | Q33: 45661.062 | R33: 45660.838 | S33: =(R33-Q33)*86000/60 -> -321.50463 | T33: =(R33-P33)*86000/60 -> 39.814815 | V33: 45663.572 | W33: =V33+TIME(0,167,0) -> 45663.688 | X33: =(W33-V33)*84600/60 -> 163.52083 | Z33: 45664.653 | AA33: 45664.687 | AB33: =(AA33-Z33)*84600/60 -> 47.979167 | AD33: =Z33-R33 -> 3.8145833 | AE33: 2 | AF33: =AE33-AD33 -> -1.8145833 | AG33: =AD33*24 -> 91.55 | AH33: =AG33-AI33 -> 36 | AI33: =((Z33 - R33) * 24) - (INT(Z33 - R33) * 12) -> 55.55 | AJ33: =I33/AI33 -> 2.8082808
A34: 45660.864 | B34: =TEXT(A34, "MMMM") -> January | D34: OMF7GZSRR | E34: DJ | F34: BYEKWASO TWAHA | G34: UBE 680K | H34: Kato Investments Ltd-Bulenga | I34: 156 | J34: A19825 | K34: OM | L34: 560 | M34: 507 | N34: =M34-L34 -> -53 | P34: =R34-TIME(0,40,0) -> 45660.826 | Q34: 45660.896 | R34: 45660.853 | S34: =(R34-Q34)*86000/60 -> -60.717593 | T34: =(R34-P34)*86000/60 -> 39.814815 | V34: 45661.69 | W34: =V34+TIME(0,175,0) -> 45661.811 | X34: =(W34-V34)*84600/60 -> 171.35417 | Z34: 45662.419 | AA34: =Z34+TIME(0,56,0) -> 45662.458 | AB34: =(AA34-Z34)*84600/60 -> 54.833333 | AD34: =Z34-R34 -> 1.5659722 | AE34: 3 | AF34: =AE34-AD34 -> 1.4340278 | AG34: =AD34*24 -> 37.583333 | AH34: =AG34-AI34 -> 12 | AI34: =((Z34 - R34) * 24) - (INT(Z34 - R34) * 12) -> 25.583333 | AJ34: =I34/AI34 -> 6.0977199
A35: 45660.985 | B35: =TEXT(A35, "MMMM") -> January | D35: OMUDTTERR | E35: DJ | F35: Kilabila Ismail | G35: UBE 419T | H35: Rugoma Traders-Kanungu/Kihihi | I35: 153.6 | J35: F15667 | K35: OM | L35: 414 | M35: =L35-1 -> 413 | N35: =M35-L35 -> -1 | P35: =R35-TIME(0,43,0) -> 45661.768 | Q35: 45661.354 | R35: 45661.798 | S35: =(R35-Q35)*86000/60 -> 636.04167 | T35: =(R35-P35)*86000/60 -> 42.800926 | V35: 45662.452 | W35: =V35+TIME(0,317,0) -> 45662.672 | X35: =(W35-V35)*84600/60 -> 310.39583 | Y35: Waited for empties from trade | Z35: 45663.47 | AA35: =Z35+TIME(0,54,0) -> 45663.508 | AB35: =(AA35-Z35)*84600/60 -> 52.875 | AD35: =Z35-R35 -> 1.6722222 | AE35: 2 | AF35: =AE35-AD35 -> 0.32777778 | AG35: =AD35*24 -> 40.133333 | AH35: =AG35-AI35 -> 12 | AI35: =((Z35 - R35) * 24) - (INT(Z35 - R35) * 12) -> 28.133333 | AJ35: =I35/AI35 -> 5.4597156
A36: 45660.986 | B36: =TEXT(A36, "MMMM") -> January | D36: OM8Y8XJRR | E36: DJ | F36: Stephen Musoke | G36: UBJ 375N | H36: Agaba Services | I36: 153.6 | J36: F15668 | K36: OM | L36: 302 | M36: 290 | N36: =M36-L36 -> -12 | P36: =R36-TIME(0,40,0) -> 45661.556 | Q36: 45661.354 | R36: 45661.583 | S36: =(R36-Q36)*86000/60 -> 328.47222 | T36: =(R36-P36)*86000/60 -> 39.814815 | V36: 45661.776 | W36: =V36+TIME(0,153,0) -> 45661.883 | X36: =(W36-V36)*84600/60 -> 149.8125 | Z36: 45662.614 | AA36: =Z36+TIME(0,57,0) -> 45662.653 | AB36: =(AA36-Z36)*84600/60 -> 55.8125 | AD36: =Z36-R36 -> 1.0305556 | AE36: 2 | AF36: =AE36-AD36 -> 0.96944444 | AG36: =AD36*24 -> 24.733333 | AH36: =AG36-AI36 -> 12 | AI36: =((Z36 - R36) * 24) - (INT(Z36 - R36) * 12) -> 12.733333 | AJ36: =I36/AI36 -> 12.062827
A37: 45660.986 | B37: =TEXT(A37, "MMMM") -> January | D37: OM4CG3KRR | E37: Manual | F37: Luyaga Isaac | G37: UAY 265V | H37: KATO INVESTMENTS LTD- KALISIZO | I37: 152.002 | J37: F15669 | K37: OM | L37: 350 | M37: 351 | N37: =M37-L37 -> 1 | P37: =R37-TIME(0,39,0) -> 45661.472 | Q37: 45661.354 | R37: 45661.499 | S37: =(R37-Q37)*86000/60 -> 208.03241 | T37: =(R37-P37)*86000/60 -> 38.819444 | V37: 45661.806 | W37: =V37+TIME(0,153,0) -> 45661.912 | X37: =(W37-V37)*84600/60 -> 149.8125 | Z37: 45662.757 | AA37: 45662.79 | AB37: =(AA37-Z37)*84600/60 -> 46.020833 | AD37: =Z37-R37 -> 1.2576389 | AE37: 2 | AF37: =AE37-AD37 -> 0.74236111 | AG37: =AD37*24 -> 30.183333 | AH37: =AG37-AI37 -> 12 | AI37: =((Z37 - R37) * 24) - (INT(Z37 - R37) * 12) -> 18.183333 | AJ37: =I37/AI37 -> 8.3594134
A38: 45661 | B38: =TEXT(A38, "MMMM") -> January | D38: OM02L7HP | E38: Manual | F38: MUKOSE MUZAMIRU | G38: UBE 690K | H38: Rugoma Traders-Rukungiri | I38: 156 | J38: Z82057 | K38: OM | L38: 256 | M38: =L38-1 -> 255 | N38: =M38-L38 -> -1 | P38: 45661.332 | Q38: 45661.312 | R38: 45661.36 | S38: =(R38-Q38)*86000/60 -> 67.685185 | T38: =(R38-P38)*86000/60 -> 39.814815 | V38: 45661.651 | W38: =V38+TIME(0,153,0) -> 45661.758 | X38: =(W38-V38)*84600/60 -> 149.8125 | Z38: 45661.876 | AA38: 45661.912 | AB38: =(AA38-Z38)*84600/60 -> 50.916667 | AD38: =Z38-R38 -> 0.51666667 | AE38: 2 | AF38: =AE38-AD38 -> 1.4833333 | AG38: =AD38*24 -> 12.4 | AH38: =AG38-AI38 -> 0 | AI38: =((Z38 - R38) * 24) - (INT(Z38 - R38) * 12) -> 12.4 | AJ38: =I38/AI38 -> 12.580645
A39: 45661 | B39: =TEXT(A39, "MMMM") -> January | D39: OM02L7EK | E39: Manual | F39: MUKOSE MUZAMIRU | G39: UBE 690K | H39: Kato Investment Ltd -Kagadi | I39: 156 | J39: A19840 | K39: OM | L39: 670 | M39: 612 | N39: =M39-L39 -> -58 | P39: =R39-TIME(0,44,0) -> 45661.306 | Q39: 45661.312 | R39: 45661.336 | S39: =(R39-Q39)*86000/60 -> 33.842593 | T39: =(R39-P39)*86000/60 -> 43.796296 | V39: 45662.482 | W39: =V39+TIME(0,175,0) -> 45662.603 | X39: =(W39-V39)*84600/60 -> 171.35417 | Z39: 45663.625 | AA39: =Z39+TIME(0,59,0) -> 45663.666 | AB39: =(AA39-Z39)*84600/60 -> 57.770833 | AD39: =Z39-R39 -> 2.2885556 | AE39: 2 | AF39: =AE39-AD39 -> -0.28855556 | AG39: =AD39*24 -> 54.925333 | AH39: =AG39-AI39 -> 24 | AI39: =((Z39 - R39) * 24) - (INT(Z39 - R39) * 12) -> 30.925333 | AJ39: =I39/AI39 -> 5.044408
A40: 45661 | B40: =TEXT(A40, "MMMM") -> January | D40: OM02L7EN | E40: Manual | G40: UBE 678K | H40: Ntale and Sons Ltd-Kakiri | I40: 156 | J40: A19842 | K40: OM | L40: 620 | M40: 602 | N40: =M40-L40 -> -18 | P40: =R40-TIME(0,44,0) -> 45661.329 | Q40: 45661.312 | R40: 45661.36 | S40: =(R40-Q40)*86000/60 -> 67.685185 | T40: =(R40-P40)*86000/60 -> 43.796296 | V40: 45661.881 | W40: =V40+TIME(0,153,0) -> 45661.987 | X40: =(W40-V40)*84600/60 -> 149.8125 | Z40: 45663.466 | AA40: 45663.5 | AB40: =(AA40-Z40)*84600/60 -> 47.979167 | AD40: =Z40-R40 -> 2.1058333 | AE40: 3 | AF40: =AE40-AD40 -> 0.89416667 | AG40: =AD40*24 -> 50.54 | AH40: =AG40-AI40 -> 24 | AI40: =((Z40 - R40) * 24) - (INT(Z40 - R40) * 12) -> 26.54 | AJ40: =I40/AI40 -> 5.8779201
A41: 45661 | B41: =TEXT(A41, "MMMM") -> January | D41: OM02L7HG | E41: Manual | F41: MUKOSE MUZAMIRU | G41: UBE 690K | H41: Kobusinge Steven-FPortal | I41: 156 | J41: Z82054 | K41: OM | L41: 390 | M41: =L41+2 -> 392 | N41: =M41-L41 -> 2 | P41: 45661.332 | Q41: 45661.312 | R41: 45661.36 | S41: =(R41-Q41)*86000/60 -> 67.685185 | T41: =(R41-P41)*86000/60 -> 39.814815 | V41: 45662.422 | W41: =V41+TIME(0,167,0) -> 45662.538 | X41: =(W41-V41)*84600/60 -> 163.52083 | Z41: 45663.452 | AA41: =Z41+TIME(0,53,0) -> 45663.489 | AB41: =(AA41-Z41)*84600/60 -> 51.895833 | AD41: =Z41-R41 -> 2.0925 | AE41: 2 | AF41: =AE41-AD41 -> -0.0925 | AG41: =AD41*24 -> 50.22 | AH41: =AG41-AI41 -> 24 | AI41: =((Z41 - R41) * 24) - (INT(Z41 - R41) * 12) -> 26.22 | AJ41: =I41/AI41 -> 5.9496568
A42: 45661 | B42: =TEXT(A42, "MMMM") -> January | D42: OM02L7HR | E42: Manual | F42: MUKOSE MUZAMIRU | G42: UBE 690K | H42: Kato Investment Ltd -Kagadi | I42: 156 | J42: A19849 | K42: OM | L42: 670 | M42: 603 | N42: =M42-L42 -> -67 | P42: =R42-TIME(0,39,0) -> 45661.537 | Q42: 45661.5 | R42: 45661.564 | S42: =(R42-Q42)*86000/60 -> 91.574074 | T42: =(R42-P42)*86000/60 -> 38.819444 | V42: 45662.647 | W42: =V42+TIME(0,175,0) -> 45662.769 | X42: =(W42-V42)*84600/60 -> 171.35417 | Z42: 45663.705 | AA42: =Z42+TIME(0,56,0) -> 45663.744 | AB42: =(AA42-Z42)*84600/60 -> 54.833333 | AD42: =Z42-R42 -> 2.1413333 | AE42: 2 | AF42: =AE42-AD42 -> -0.14133333 | AG42: =AD42*24 -> 51.392 | AH42: =AG42-AI42 -> 24 | AI42: =((Z42 - R42) * 24) - (INT(Z42 - R42) * 12) -> 27.392 | AJ42: =I42/AI42 -> 5.6950935
A43: 45661 | B43: =TEXT(A43, "MMMM") -> January | D43: OM02L7HJ | E43: Manual | G43: UBE 678K | H43: Kabaco U Ltd | I43: 156 | J43: Z82055 | K43: OM | L43: 320 | M43: 321 | N43: =M43-L43 -> 1 | P43: 45661.332 | Q43: 45661.312 | R43: 45661.36 | S43: =(R43-Q43)*86000/60 -> 67.685185 | T43: =(R43-P43)*86000/60 -> 39.814815 | V43: 45661.61 | W43: =V43+TIME(0,149,0) -> 45661.713 | X43: =(W43-V43)*84600/60 -> 145.89583 | Z43: 45662.419 | AA43: 45662.453 | AB43: =(AA43-Z43)*84600/60 -> 47.979167 | AD43: =Z43-R43 -> 1.0591667 | AE43: 2 | AF43: =AE43-AD43 -> 0.94083333 | AG43: =AD43*24 -> 25.42 | AH43: =AG43-AI43 -> 12 | AI43: =((Z43 - R43) * 24) - (INT(Z43 - R43) * 12) -> 13.42 | AJ43: =I43/AI43 -> 11.624441
A44: 45661 | B44: =TEXT(A44, "MMMM") -> January | D44: OM02L7HQ | E44: Manual | G44: UBE 678K | H44: Kobusinge Steven-Kamwenge | I44: 156 | J44: Z82058 | K44: OM | L44: 230 | M44: =L44-1 -> 229 | N44: =M44-L44 -> -1 | P44: 45661.332 | Q44: 45661.312 | R44: 45661.36 | S44: =(R44-Q44)*86000/60 -> 67.685185 | T44: =(R44-P44)*86000/60 -> 39.814815 | V44: 45662.381 | W44: =V44+TIME(0,153,0) -> 45662.487 | X44: =(W44-V44)*84600/60 -> 149.8125 | Z44: 45662.787 | AA44: 45662.822 | AB44: =(AA44-Z44)*84600/60 -> 47.979167 | AD44: =Z44-R44 -> 1.4277778 | AE44: 2 | AF44: =AE44-AD44 -> 0.57222222 | AG44: =AD44*24 -> 34.266667 | AH44: =AG44-AI44 -> 12 | AI44: =((Z44 - R44) * 24) - (INT(Z44 - R44) * 12) -> 22.266667 | AJ44: =I44/AI44 -> 7.005988
A45: 45661.482 | B45: =TEXT(A45, "MMMM") -> January | D45: OMWYCZRRR | E45: DJ | F45: Konge Husein | G45: UBJ 707D | H45: KATO INVESTMENTS LTD- KALISIZO | I45: 153.6 | J45: F15670 | K45: OM | L45: 350 | M45: 351 | N45: =M45-L45 -> 1 | P45: =R45-TIME(0,40,0) -> 45661.633 | Q45: 45662.333 | R45: 45661.66 | S45: =(R45-Q45)*86000/60 -> -964.51389 | T45: =(R45-P45)*86000/60 -> 39.814815 | V45: 45662.392 | W45: =V45+TIME(0,167,0) -> 45662.508 | X45: =(W45-V45)*84600/60 -> 163.52083 | Z45: 45663.517 | AA45: =Z45+TIME(0,59,0) -> 45663.558 | AB45: =(AA45-Z45)*84600/60 -> 57.770833 | AD45: =Z45-R45 -> 1.8569444 | AE45: 2 | AF45: =AE45-AD45 -> 0.14305556 | AG45: =AD45*24 -> 44.566667 | AH45: =AG45-AI45 -> 12 | AI45: =((Z45 - R45) * 24) - (INT(Z45 - R45) * 12) -> 32.566667 | AJ45: =I45/AI45 -> 4.716479
A46: 45661.487 | B46: =TEXT(A46, "MMMM") -> January | D46: OM2E5A6RR | E46: DJ | F46: Jacob Oneka | G46: UBE 422T | H46: KATO INVESTMENTS LIMITED-MASAK | I46: 153.6 | J46: F15671 | K46: OM | L46: 340 | M46: 299 | N46: =M46-L46 -> -41 | P46: =R46-TIME(0,63,0) -> 45661.583 | Q46: 45662.176 | R46: 45661.627 | S46: =(R46-Q46)*86000/60 -> -787.33796 | T46: =(R46-P46)*86000/60 -> 62.708333 | U46: Pre-Trip inspection defect closure | V46: 45661.78 | W46: =V46+TIME(0,153,0) -> 45661.886 | X46: =(W46-V46)*84600/60 -> 149.8125 | Z46: 45662.743 | AA46: =Z46+TIME(0,54,0) -> 45662.781 | AB46: =(AA46-Z46)*84600/60 -> 52.875 | AD46: =Z46-R46 -> 1.1159722 | AE46: 2 | AF46: =AE46-AD46 -> 0.88402778 | AG46: =AD46*24 -> 26.783333 | AH46: =AG46-AI46 -> 12 | AI46: =((Z46 - R46) * 24) - (INT(Z46 - R46) * 12) -> 14.783333 | AJ46: =I46/AI46 -> 10.390079
A47: 45661.818 | B47: =TEXT(A47, "MMMM") -> January | D47: OMO3M45RR | E47: DJ | F47: NASASIRA STEPHENE | G47: UBK 882R | H47: Kato Investment Ltd -Mityana | I47: 187.2 | J47: A19850 | K47: OM | L47: 690 | M47: =L47+2 -> 692 | N47: =M47-L47 -> 2 | P47: =R47-TIME(0,57,0) -> 45662.419 | Q47: 45661.875 | R47: 45662.458 | S47: =(R47-Q47)*86000/60 -> 836.11111 | T47: =(R47-P47)*86000/60 -> 56.736111 | U47: DJ failures | V47: 45663.428 | W47: =V47+TIME(0,153,0) -> 45663.535 | X47: =(W47-V47)*84600/60 -> 149.8125 | Z47: 45664.267 | AA47: =Z47+TIME(0,56,0) -> 45664.306 | AB47: =(AA47-Z47)*84600/60 -> 54.833333 | AD47: =Z47-R47 -> 1.8090278 | AE47: 2 | AF47: =AE47-AD47 -> 0.19097222 | AG47: =AD47*24 -> 43.416667 | AH47: =AG47-AI47 -> 12 | AI47: =((Z47 - R47) * 24) - (INT(Z47 - R47) * 12) -> 31.416667 | AJ47: =I47/AI47 -> 5.9586207
A48: 45661.818 | B48: =TEXT(A48, "MMMM") -> January | D48: OMCD8ZSRR | E48: Manual | G48: UBJ 417C | H48: Boniface Harera | I48: 156 | J48: F15672 | K48: OM | L48: 470 | M48: 465 | N48: =M48-L48 -> -5 | P48: =R48-TIME(0,42,0) -> 45662.353 | Q48: 45662.318 | R48: 45662.382 | S48: =(R48-Q48)*86000/60 -> 91.574074 | T48: =(R48-P48)*86000/60 -> 41.805556 | V48: 45663.445 | W48: =V48+TIME(0,158,0) -> 45663.555 | X48: =(W48-V48)*84600/60 -> 154.70833 | Z48: 45664.614 | AA48: =Z48+TIME(0,57,0) -> 45664.653 | AB48: =(AA48-Z48)*84600/60 -> 55.8125 | AD48: =Z48-R48 -> 2.23125 | AE48: 2 | AF48: =AE48-AD48 -> -0.23125 | AG48: =AD48*24 -> 53.55 | AH48: =AG48-AI48 -> 24 | AI48: =((Z48 - R48) * 24) - (INT(Z48 - R48) * 12) -> 29.55 | AJ48: =I48/AI48 -> 5.2791878
A49: 45661.82 | B49: =TEXT(A49, "MMMM") -> January | D49: OMA2QVIRR | E49: DJ | F49: Tumusiime Robert | G49: UBJ 988D | H49: Agaba Services | I49: 153.6 | J49: F15673 | K49: OM | L49: 302 | M49: 291 | N49: =M49-L49 -> -11 | P49: =R49-TIME(0,43,0) -> 45662.319 | Q49: 45662.177 | R49: 45662.349 | S49: =(R49-Q49)*86000/60 -> 245.85648 | T49: =(R49-P49)*86000/60 -> 42.800926 | V49: 45662.591 | W49: =V49+TIME(0,161,0) -> 45662.703 | X49: =(W49-V49)*84600/60 -> 157.64583 | Z49: 45663.448 | AA49: 45663.484 | AB49: =(AA49-Z49)*84600/60 -> 50.916667 | AD49: =Z49-R49 -> 1.0993056 | AE49: 2 | AF49: =AE49-AD49 -> 0.90069444 | AG49: =AD49*24 -> 26.383333 | AH49: =AG49-AI49 -> 12 | AI49: =((Z49 - R49) * 24) - (INT(Z49 - R49) * 12) -> 14.383333 | AJ49: =I49/AI49 -> 10.679027
A50: 45661.83 | B50: =TEXT(A50, "MMMM") -> January | D50: OMG49BWRR | E50: Manual | F50: Hamudi Sesanga | G50: UAT 351G | H50: RUGOMA TRADERS CO. LTD NTUNGAM | I50: 153.6 | J50: F15674 | K50: OM | L50: 130 | M50: =L50-1 -> 129 | N50: =M50-L50 -> -1 | P50: =R50-TIME(0,40,0) -> 45662.352 | Q50: 45662.33 | R50: 45662.38 | S50: =(R50-Q50)*86000/60 -> 71.666667 | T50: =(R50-P50)*86000/60 -> 39.814815 | V50: 45662.484 | W50: =V50+TIME(0,237,0) -> 45662.649 | X50: =(W50-V50)*84600/60 -> 232.0625 | Y50: found another truck at the RD | Z50: 45662.88 | AA50: 45662.917 | AB50: =(AA50-Z50)*84600/60 -> 51.895833 | AD50: =Z50-R50 -> 0.5 | AE50: 1 | AF50: =AE50-AD50 -> 0.5 | AG50: =AD50*24 -> 12 | AH50: =AG50-AI50 -> 0 | AI50: =((Z50 - R50) * 24) - (INT(Z50 - R50) * 12) -> 12 | AJ50: =I50/AI50 -> 12.8
A51: 45661.85 | B51: =TEXT(A51, "MMMM") -> January | D51: OM96U3ORR | E51: DJ | F51: Kabene John | G51: UBA 523T | H51: Ntale and Sons | I51: 153.6 | J51: A19851 | K51: OM | L51: 810 | M51: 812 | N51: =M51-L51 -> 2 | P51: =R51-TIME(0,40,0) -> 45663.44 | Q51: 45661.896 | R51: 45663.467 | S51: =(R51-Q51)*86000/60 -> 2252.5231 | T51: =(R51-P51)*86000/60 -> 39.814815 | V51: 45664.424 | W51: =V51+TIME(0,153,0) -> 45664.53 | X51: =(W51-V51)*84600/60 -> 149.8125 | Z51: 45665.621 | AA51: =Z51+TIME(0,54,0) -> 45665.658 | AB51: =(AA51-Z51)*84600/60 -> 52.875 | AD51: =Z51-R51 -> 2.1534722 | AE51: 3 | AF51: =AE51-AD51 -> 0.84652778 | AG51: =AD51*24 -> 51.683333 | AH51: =AG51-AI51 -> 24 | AI51: =((Z51 - R51) * 24) - (INT(Z51 - R51) * 12) -> 27.683333 | AJ51: =I51/AI51 -> 5.5484648
A52: 45661.967 | B52: =TEXT(A52, "MMMM") -> January | D52: OM4RC6WRR | E52: DJ | F52: Mugisha George | G52: UAV 203T | H52: Kato Investments Ltd-Bulenga | I52: 153.6 | J52: A19856 | K52: OM | L52: 560 | M52: =L52-1 -> 559 | N52: =M52-L52 -> -1 | P52: =R52-TIME(0,43,0) -> 45662.663 | Q52: 45662.842 | R52: 45662.693 | S52: =(R52-Q52)*86000/60 -> -214.00463 | T52: =(R52-P52)*86000/60 -> 42.800926 | V52: 45663.499 | W52: =V52+TIME(0,161,0) -> 45663.61 | X52: =(W52-V52)*84600/60 -> 157.64583 | Z52: 45665.501 | AA52: =Z52+TIME(0,57,0) -> 45665.541 | AB52: =(AA52-Z52)*84600/60 -> 55.8125 | AD52: =Z52-R52 -> 2.8083333 | AE52: 3 | AF52: =AE52-AD52 -> 0.19166667 | AG52: =AD52*24 -> 67.4 | AH52: =AG52-AI52 -> 24 | AI52: =((Z52 - R52) * 24) - (INT(Z52 - R52) * 12) -> 43.4 | AJ52: =I52/AI52 -> 3.5391705
A53: 45661.968 | B53: =TEXT(A53, "MMMM") -> January | D53: OM9SFUBRR | E53: Manual | F53: Kabene John | G53: UBA 523T | H53: Kabaco U Ltd-Mbarara | I53: 153.6 | J53: Z82060 | K53: OM | L53: 20 | M53: 12 | N53: =M53-L53 -> -8 | P53: =R53-TIME(0,40,0) -> 45662.493 | Q53: 45662.468 | R53: 45662.521 | S53: =(R53-Q53)*86000/60 -> 74.652778 | T53: =(R53-P53)*86000/60 -> 39.814815 | V53: 45662.542 | W53: =V53+TIME(0,161,0) -> 45662.654 | X53: =(W53-V53)*84600/60 -> 157.64583 | Z53: 45662.728 | AA53: =Z53+TIME(0,59,0) -> 45662.769 | AB53: =(AA53-Z53)*84600/60 -> 57.770833 | AD53: =Z53-R53 -> 0.20763889 | AE53: 2 | AF53: =AE53-AD53 -> 1.7923611 | AG53: =AD53*24 -> 4.9833333 | AH53: =AG53-AI53 -> 0 | AI53: =((Z53 - R53) * 24) - (INT(Z53 - R53) * 12) -> 4.9833333 | AJ53: =I53/AI53 -> 30.822742
A54: 45661.979 | B54: =TEXT(A54, "MMMM") -> January | D54: OMC6AUJRR | E54: Manual | F54: Angello Lumala | G54: UAV 051U | H54: KATO INVESTMENTS LTD- KALISIZO | I54: 153.6 | J54: F15675 | K54: OM | L54: 350 | M54: 351 | N54: =M54-L54 -> 1 | P54: =R54-TIME(0,49,0) -> 45662.506 | Q54: 45662.479 | R54: 45662.54 | S54: =(R54-Q54)*86000/60 -> 87.592593 | T54: =(R54-P54)*86000/60 -> 48.773148 | U54: Driver delays | V54: 45662.832 | W54: =V54+TIME(0,175,0) -> 45662.953 | X54: =(W54-V54)*84600/60 -> 171.35417 | Z54: 45663.798 | AA54: 45663.838 | AB54: =(AA54-Z54)*84600/60 -> 55.8125 | AD54: =Z54-R54 -> 1.258 | AE54: 2 | AF54: =AE54-AD54 -> 0.742 | AG54: =AD54*24 -> 30.192 | AH54: =AG54-AI54 -> 12 | AI54: =((Z54 - R54) * 24) - (INT(Z54 - R54) * 12) -> 18.192 | AJ54: =I54/AI54 -> 8.4432718
A55: 45662 | B55: =TEXT(A55, "MMMM") -> January | D55: OM02L7NZ | E55: Manual | F55: MUKOSE MUZAMIRU | G55: UBE 690K | H55: Rugoma Traders-Rukungiri | I55: 156 | J55: Z82079 | K55: OM | L55: 256 | M55: =L55-1 -> 255 | N55: =M55-L55 -> -1 | P55: =R55-TIME(0,43,0) -> 45662.347 | Q55: 45662.312 | R55: 45662.376 | S55: =(R55-Q55)*86000/60 -> 91.574074 | T55: =(R55-P55)*86000/60 -> 42.800926 | V55: 45662.675 | W55: =V55+TIME(0,153,0) -> 45662.781 | X55: =(W55-V55)*84600/60 -> 149.8125 | Z55: 45662.9 | AA55: =Z55+TIME(0,56,0) -> 45662.939 | AB55: =(AA55-Z55)*84600/60 -> 54.833333 | AD55: =Z55-R55 -> 0.52361111 | AE55: 2 | AF55: =AE55-AD55 -> 1.4763889 | AG55: =AD55*24 -> 12.566667 | AH55: =AG55-AI55 -> 0 | AI55: =((Z55 - R55) * 24) - (INT(Z55 - R55) * 12) -> 12.566667 | AJ55: =I55/AI55 -> 12.413793
A56: 45662 | B56: =TEXT(A56, "MMMM") -> January | D56: OM02L7P3 | E56: Manual | G56: UBE 687K | H56: Kobusinge Steven-Kamwenge | I56: 156 | J56: Z82080 | K56: OM | L56: 230 | M56: 234 | N56: =M56-L56 -> 4 | P56: =R56-TIME(0,43,0) -> 45662.333 | Q56: 45662.312 | R56: 45662.362 | S56: =(R56-Q56)*86000/60 -> 71.666667 | T56: =(R56-P56)*86000/60 -> 42.800926 | V56: 45663.383 | W56: =V56+TIME(0,149,0) -> 45663.487 | X56: =(W56-V56)*84600/60 -> 145.89583 | Z56: 45663.701 | AA56: =Z56+TIME(0,58,0) -> 45663.741 | AB56: =(AA56-Z56)*84600/60 -> 56.791667 | AD56: =Z56-R56 -> 1.3381944 | AE56: 2 | AF56: =AE56-AD56 -> 0.66180556 | AG56: =AD56*24 -> 32.116667 | AH56: =AG56-AI56 -> 12 | AI56: =((Z56 - R56) * 24) - (INT(Z56 - R56) * 12) -> 20.116667 | AJ56: =I56/AI56 -> 7.7547639
A57: 45662 | B57: =TEXT(A57, "MMMM") -> January | D57: OM02L7NY | E57: Manual | G57: UBP 311H | H57: Kobusinge Steven-FPortal | I57: 156 | J57: Z82078 | K57: OM | L57: 390 | M57: =L57-2 -> 388 | N57: =M57-L57 -> -2 | P57: =R57-TIME(0,63,0) -> 45662.322 | Q57: 45662.312 | R57: 45662.365 | S57: =(R57-Q57)*86000/60 -> 75.648148 | T57: =(R57-P57)*86000/60 -> 62.708333 | U57: DJ failures | V57: 45663.428 | W57: =V57+TIME(0,247,0) -> 45663.599 | X57: =(W57-V57)*84600/60 -> 241.85417 | Y57: truck faulty | Z57: 45664.372 | AA57: =Z57+TIME(0,57,0) -> 45664.411 | AB57: =(AA57-Z57)*84600/60 -> 55.8125 | AD57: =Z57-R57 -> 2.0065 | AE57: 2 | AF57: =AE57-AD57 -> -0.0065 | AG57: =AD57*24 -> 48.156 | AH57: =AG57-AI57 -> 24 | AI57: =((Z57 - R57) * 24) - (INT(Z57 - R57) * 12) -> 24.156 | AJ57: =I57/AI57 -> 6.4580229
A58: 45662 | B58: =TEXT(A58, "MMMM") -> January | D58: OM02L7PK | E58: Manual | F58: MUKOSE MUZAMIRU | G58: UBE 690K | H58: Kobusinge Acaali- Kyenjojo | I58: 156 | J58: Z82081 | K58: OM | L58: 480 | M58: =L58-1 -> 479 | N58: =M58-L58 -> -1 | P58: =R58-TIME(0,40,0) -> 45662.332 | Q58: 45662.312 | R58: 45662.36 | S58: =(R58-Q58)*86000/60 -> 67.685185 | T58: =(R58-P58)*86000/60 -> 39.814815 | V58: 45663.443 | W58: =V58+TIME(0,153,0) -> 45663.549 | X58: =(W58-V58)*84600/60 -> 149.8125 | Z58: 45664.684 | AA58: 45664.723 | AB58: =(AA58-Z58)*84600/60 -> 55.8125 | AD58: =Z58-R58 -> 2.3241222 | AE58: 2 | AF58: =AE58-AD58 -> -0.32412222 | AG58: =AD58*24 -> 55.778933 | AH58: =AG58-AI58 -> 24 | AI58: =((Z58 - R58) * 24) - (INT(Z58 - R58) * 12) -> 31.778933 | AJ58: =I58/AI58 -> 4.9089124
A59: 45662 | B59: =TEXT(A59, "MMMM") -> January | D59: OM02L7LG | E59: Manual | G59: UBP 311H | H59: Kabaco U Ltd | I59: 156 | J59: Z82067 | K59: OM | L59: 320 | M59: 323 | N59: =M59-L59 -> 3 | P59: =R59-TIME(0,44,0) -> 45662.519 | Q59: 45662.5 | R59: 45662.55 | S59: =(R59-Q59)*86000/60 -> 71.666667 | T59: =(R59-P59)*86000/60 -> 43.796296 | V59: 45662.8 | W59: =V59+TIME(0,149,0) -> 45662.903 | X59: =(W59-V59)*84600/60 -> 145.89583 | Z59: 45664.305 | AA59: =Z59+TIME(0,57,0) -> 45664.345 | AB59: =(AA59-Z59)*84600/60 -> 55.8125 | AD59: =Z59-R59 -> 1.755 | AE59: 2 | AF59: =AE59-AD59 -> 0.245 | AG59: =AD59*24 -> 42.12 | AH59: =AG59-AI59 -> 12 | AI59: =((Z59 - R59) * 24) - (INT(Z59 - R59) * 12) -> 30.12 | AJ59: =I59/AI59 -> 5.1792829
A60: 45662 | B60: =TEXT(A60, "MMMM") -> January | D60: OM02L7NX | E60: Manual | F60: Ekwalikwa Yusuf | G60: UBP 311H | H60: Kobusinge Steven-FPortal | I60: 156 | J60: Z82077 | K60: OM | L60: 390 | M60: =L60+2 -> 392 | N60: =M60-L60 -> 2 | P60: =R60-TIME(0,59,0) -> 45662.319 | Q60: 45662.312 | R60: 45662.36 | S60: =(R60-Q60)*86000/60 -> 67.685185 | T60: =(R60-P60)*86000/60 -> 58.726852 | U60: Jam at the weigh bridge | V60: 45663.422 | W60: =V60+TIME(0,153,0) -> 45663.528 | X60: =(W60-V60)*84600/60 -> 149.8125 | Z60: 45664.552 | AA60: =Z60+TIME(0,59,0) -> 45664.593 | AB60: =(AA60-Z60)*84600/60 -> 57.770833 | AD60: =Z60-R60 -> 2.1925 | AE60: 2 | AF60: =AE60-AD60 -> -0.1925 | AG60: =AD60*24 -> 52.62 | AH60: =AG60-AI60 -> 24 | AI60: =((Z60 - R60) * 24) - (INT(Z60 - R60) * 12) -> 28.62 | AJ60: =I60/AI60 -> 5.4507338
A61: 45662 | B61: =TEXT(A61, "MMMM") -> January | D61: OM02L7LH | E61: Manual | F61: Ekwalikwa Yusuf | G61: UBP 311H | H61: Kobusinge Steven-FPortal | I61: 156 | J61: Z82068 | K61: OM | L61: 390 | M61: =L61+2 -> 392 | N61: =M61-L61 -> 2 | P61: =R61-TIME(0,39,0) -> 45662.343 | Q61: 45662.312 | R61: 45662.37 | S61: =(R61-Q61)*86000/60 -> 82.615741 | T61: =(R61-P61)*86000/60 -> 38.819444 | V61: 45663.433 | W61: =V61+TIME(0,175,0) -> 45663.554 | X61: =(W61-V61)*84600/60 -> 171.35417 | Z61: 45664.463 | AA61: 45664.502 | AB61: =(AA61-Z61)*84600/60 -> 55.8125 | AD61: =Z61-R61 -> 2.0925 | AE61: 2 | AF61: =AE61-AD61 -> -0.0925 | AG61: =AD61*24 -> 50.22 | AH61: =AG61-AI61 -> 24 | AI61: =((Z61 - R61) * 24) - (INT(Z61 - R61) * 12) -> 26.22 | AJ61: =I61/AI61 -> 5.9496568
A62: 45662 | B62: =TEXT(A62, "MMMM") -> January | D62: OM02L7NV | E62: Manual | G62: UBP 311H | H62: Kato Investments Ltd- Kakumiro | I62: 156 | J62: A19875 | K62: OM | L62: 765 | M62: =L62-1 -> 764 | N62: =M62-L62 -> -1 | P62: 45662.332 | Q62: 45662.312 | R62: 45662.36 | S62: =(R62-Q62)*86000/60 -> 67.685185 | T62: =(R62-P62)*86000/60 -> 39.814815 | V62: 45662.735 | W62: =V62+TIME(0,149,0) -> 45662.838 | X62: =(W62-V62)*84600/60 -> 145.89583 | Z62: 45664.279 | AA62: 45664.318 | AB62: =(AA62-Z62)*84600/60 -> 55.8125 | AD62: =Z62-R62 -> 1.919 | AE62: 3 | AF62: =AE62-AD62 -> 1.081 | AG62: =AD62*24 -> 46.056 | AH62: =AG62-AI62 -> 12 | AI62: =((Z62 - R62) * 24) - (INT(Z62 - R62) * 12) -> 34.056 | AJ62: =I62/AI62 -> 4.5806906
A63: 45662 | B63: =TEXT(A63, "MMMM") -> January | D63: OM02L7P1 | E63: Manual | F63: MUKOSE MUZAMIRU | G63: UBE 690K | H63: KATO INVESTMENTS LTD-KATIKARA | I63: 156 | J63: A19877 | K63: OM | L63: 790 | M63: =L63-2 -> 788 | N63: =M63-L63 -> -2 | P63: =R63-TIME(0,39,0) -> 45662.339 | Q63: 45662.312 | R63: 45662.366 | S63: =(R63-Q63)*86000/60 -> 76.643519 | T63: =(R63-P63)*86000/60 -> 38.819444 | V63: 45663.439 | W63: =V63+TIME(0,367,0) -> 45663.694 | X63: =(W63-V63)*84600/60 -> 359.35417 | Y63: slept at the RD and offloaded the next day | Z63: 45664.778 | AA63: =Z63+TIME(0,58,0) -> 45664.819 | AB63: =(AA63-Z63)*84600/60 -> 56.791667 | AD63: =Z63-R63 -> 2.4125 | AE63: 3 | AF63: =AE63-AD63 -> 0.5875 | AG63: =AD63*24 -> 57.9 | AH63: =AG63-AI63 -> 24 | AI63: =((Z63 - R63) * 24) - (INT(Z63 - R63) * 12) -> 33.9 | AJ63: =I63/AI63 -> 4.6017699
A64: 45662 | B64: =TEXT(A64, "MMMM") -> January | D64: OM02L7LJ | E64: Manual | G64: UBP 311H | H64: KATO INVESTMENTS LTD-KATIKARA | I64: 156 | J64: A19867 | K64: OM | L64: 790 | M64: =L64-2 -> 788 | N64: =M64-L64 -> -2 | P64: 45662.332 | Q64: 45662.312 | R64: 45662.36 | S64: =(R64-Q64)*86000/60 -> 67.685185 | T64: =(R64-P64)*86000/60 -> 39.814815 | V64: 45663.412 | W64: =V64+TIME(0,175,0) -> 45663.533 | X64: =(W64-V64)*84600/60 -> 171.35417 | Z64: 45664.819 | AA64: =Z64+TIME(0,57,0) -> 45664.859 | AB64: =(AA64-Z64)*84600/60 -> 55.8125 | AD64: =Z64-R64 -> 2.4597222 | AE64: 3 | AF64: =AE64-AD64 -> 0.54027778 | AG64: =AD64*24 -> 59.033333 | AH64: =AG64-AI64 -> 24 | AI64: =((Z64 - R64) * 24) - (INT(Z64 - R64) * 12) -> 35.033333 | AJ64: =I64/AI64 -> 4.452902
A65: 45662.55 | B65: =TEXT(A65, "MMMM") -> January | D65: OMWSZKWRR | E65: DJ | F65: Benon Ssempijja | G65: UAY 526V | H65: Rugoma Traders-Kanungu/Kihihi | I65: 153.6 | J65: F15677 | K65: OM | L65: 414 | M65: =L65-1 -> 413 | N65: =M65-L65 -> -1 | P65: =R65-TIME(0,76,0) -> 45662.707 | Q65: 45663.083 | R65: 45662.76 | S65: =(R65-Q65)*86000/60 -> -462.84722 | T65: =(R65-P65)*86000/60 -> 75.648148 | U65: DJ failures | V65: 45663.514 | W65: =V65+TIME(0,149,0) -> 45663.617 | X65: =(W65-V65)*84600/60 -> 145.89583 | Z65: 45664.525 | AA65: 45664.578 | AB65: =(AA65-Z65)*84600/60 -> 75.395833 | AC65: fuel delays | AD65: =Z65-R65 -> 1.7652778 | AE65: 2 | AF65: =AE65-AD65 -> 0.23472222 | AG65: =AD65*24 -> 42.366667 | AH65: =AG65-AI65 -> 12 | AI65: =((Z65 - R65) * 24) - (INT(Z65 - R65) * 12) -> 30.366667 | AJ65: =I65/AI65 -> 5.0581778
A66: 45662.551 | B66: =TEXT(A66, "MMMM") -> January | D66: OMIUJ2ERR | E66: Manual | F66: Godwin Niwensiima | G66: UAR 731Q | H66: Kabaco U Ltd-Mbarara | I66: 153.6 | J66: Z82066 | K66: OM | L66: 20 | M66: 12 | N66: =M66-L66 -> -8 | P66: 45663.571 | Q66: 45663.051 | R66: 45663.599 | S66: =(R66-Q66)*86000/60 -> 784.35185 | T66: =(R66-P66)*86000/60 -> 39.814815 | V66: 45663.624 | W66: =V66+TIME(0,197,0) -> 45663.76 | X66: =(W66-V66)*84600/60 -> 192.89583 | Y66: Waited for empties from trade | Z66: 45663.796 | AA66: =Z66+TIME(0,56,0) -> 45663.835 | AB66: =(AA66-Z66)*84600/60 -> 54.833333 | AD66: =Z66-R66 -> 0.19791667 | AE66: 2 | AF66: =AE66-AD66 -> 1.8020833 | AG66: =AD66*24 -> 4.75 | AH66: =AG66-AI66 -> 0 | AI66: =((Z66 - R66) * 24) - (INT(Z66 - R66) * 12) -> 4.75 | AJ66: =I66/AI66 -> 32.336842
A67: 45662.607 | B67: =TEXT(A67, "MMMM") -> January | D67: OMNWADWRR | E67: Manual | G67: UBJ 419C | H67: Ntale and Sons Ltd-Kakiri | I67: 156 | J67: A19868 | K67: OM | L67: 620 | M67: 602 | N67: =M67-L67 -> -18 | P67: =R67-TIME(0,57,0) -> 45663.12 | Q67: 45663.107 | R67: 45663.159 | S67: =(R67-Q67)*86000/60 -> 74.652778 | T67: =(R67-P67)*86000/60 -> 56.736111 | U67: DJ failures | V67: 45663.68 | W67: =V67+TIME(0,149,0) -> 45663.784 | X67: =(W67-V67)*84600/60 -> 145.89583 | Z67: 45665.39 | AA67: 45665.43 | AB67: =(AA67-Z67)*84600/60 -> 55.8125 | AD67: =Z67-R67 -> 2.2308333 | AE67: 3 | AF67: =AE67-AD67 -> 0.76916667 | AG67: =AD67*24 -> 53.54 | AH67: =AG67-AI67 -> 24 | AI67: =((Z67 - R67) * 24) - (INT(Z67 - R67) * 12) -> 29.54 | AJ67: =I67/AI67 -> 5.2809749
A68: 45662.609 | B68: =TEXT(A68, "MMMM") -> January | D68: OMZFBPWRR | E68: DJ | F68: James Kironde | G68: UBK 881R | H68: KATO INVESTMENTS LIMITED-MASAK | I68: 153.6 | J68: F15679 | K68: OM | L68: 340 | M68: =L68-1 -> 339 | N68: =M68-L68 -> -1 | P68: =R68-TIME(0,49,0) -> 45664.272 | Q68: 45663.176 | R68: 45664.306 | S68: =(R68-Q68)*86000/60 -> 1619.4676 | T68: =(R68-P68)*86000/60 -> 48.773148 | U68: Jam at the weigh bridge | V68: 45664.515 | W68: =V68+TIME(0,175,0) -> 45664.636 | X68: =(W68-V68)*84600/60 -> 171.35417 | Z68: 45665.519 | AA68: 45665.553 | AB68: =(AA68-Z68)*84600/60 -> 47.979167 | AD68: =Z68-R68 -> 1.2125 | AE68: 2 | AF68: =AE68-AD68 -> 0.7875 | AG68: =AD68*24 -> 29.1 | AH68: =AG68-AI68 -> 12 | AI68: =((Z68 - R68) * 24) - (INT(Z68 - R68) * 12) -> 17.1 | AJ68: =I68/AI68 -> 8.9824561
A69: 45662.61 | B69: =TEXT(A69, "MMMM") -> January | D69: OMXTBKSRR | E69: DJ | F69: Isaac Tumuhimbise | G69: UBE 287X | H69: KATO INVESTMENTS LIMITED-MASAK | I69: 153.6 | J69: F15680 | K69: OM | L69: 340 | M69: =L69-1 -> 339 | N69: =M69-L69 -> -1 | P69: =R69-TIME(0,41,0) -> 45662.783 | Q69: 45663.176 | R69: 45662.811 | S69: =(R69-Q69)*86000/60 -> -523.56481 | T69: =(R69-P69)*86000/60 -> 40.810185 | V69: 45663.433 | W69: =V69+TIME(0,171,0) -> 45663.551 | X69: =(W69-V69)*84600/60 -> 167.4375 | Z69: 45664.576 | AA69: 45664.615 | AB69: =(AA69-Z69)*84600/60 -> 54.833333 | AD69: =Z69-R69 -> 1.7645833 | AE69: 2 | AF69: =AE69-AD69 -> 0.23541667 | AG69: =AD69*24 -> 42.35 | AH69: =AG69-AI69 -> 12 | AI69: =((Z69 - R69) * 24) - (INT(Z69 - R69) * 12) -> 30.35 | AJ69: =I69/AI69 -> 5.0609555
A70: 45662.663 | B70: =TEXT(A70, "MMMM") -> January | D70: OMK5QNURR | E70: Manual | F70: Godwin Niwensiima | G70: UAR 731Q | H70: Kabaco U Ltd-Mbarara | I70: 153.6 | J70: Z82069 | K70: OM | L70: 20 | M70: 12 | N70: =M70-L70 -> -8 | P70: =R70-TIME(0,40,0) -> 45663.446 | Q70: 45663.163 | R70: 45663.474 | S70: =(R70-Q70)*86000/60 -> 445.92593 | T70: =(R70-P70)*86000/60 -> 39.814815 | V70: 45663.491 | W70: =V70+TIME(0,367,0) -> 45663.746 | X70: =(W70-V70)*84600/60 -> 359.35417 | Y70: found another truck at the RD | Z70: 45663.65 | AA70: =Z70+TIME(0,58,0) -> 45663.691 | AB70: =(AA70-Z70)*84600/60 -> 56.791667 | AD70: =Z70-R70 -> 0.17638889 | AE70: 2 | AF70: =AE70-AD70 -> 1.8236111 | AG70: =AD70*24 -> 4.2333333 | AH70: =AG70-AI70 -> 0 | AI70: =((Z70 - R70) * 24) - (INT(Z70 - R70) * 12) -> 4.2333333 | AJ70: =I70/AI70 -> 36.283465
A71: 45662.7 | B71: =TEXT(A71, "MMMM") -> January | D71: OMQO9OURR | E71: DJ | F71: Jacob Oneka | G71: UBE 422T | H71: Kabaco U Ltd | I71: 153.6 | J71: Z82071 | K71: OM | L71: 320 | M71: 320 | N71: =M71-L71 -> 0 | P71: =R71-TIME(0,40,0) -> 45662.796 | Q71: 45663.099 | R71: 45662.824 | S71: =(R71-Q71)*86000/60 -> -394.16667 | T71: =(R71-P71)*86000/60 -> 39.814815 | V71: 45662.999 | W71: =V71+TIME(0,167,0) -> 45663.115 | X71: =(W71-V71)*84600/60 -> 163.52083 | Z71: 45663.503 | AA71: =Z71+TIME(0,57,0) -> 45663.542 | AB71: =(AA71-Z71)*84600/60 -> 55.8125 | AD71: =Z71-R71 -> 0.67916667 | AE71: 2 | AF71: =AE71-AD71 -> 1.3208333 | AG71: =AD71*24 -> 16.3 | AH71: =AG71-AI71 -> 0 | AI71: =((Z71 - R71) * 24) - (INT(Z71 - R71) * 12) -> 16.3 | AJ71: =I71/AI71 -> 9.4233129
A72: 45662.701 | B72: =TEXT(A72, "MMMM") -> January | D72: OM42HHBRR | E72: Manual | F72: SENTONG DAVID | G72: UBP 298H | H72: Kabaco U Ltd | I72: 156 | J72: Z82072 | K72: OM | L72: 320 | M72: 321 | N72: =M72-L72 -> 1 | P72: =R72-TIME(0,59,0) -> 45662.692 | Q72: 45663.099 | R72: 45662.733 | S72: =(R72-Q72)*86000/60 -> -524.56019 | T72: =(R72-P72)*86000/60 -> 58.726852 | U72: Reconciling stock count delays | V72: 45663.334 | W72: =V72+TIME(0,171,0) -> 45663.453 | X72: =(W72-V72)*84600/60 -> 167.4375 | Z72: 45664.622 | AA72: =Z72+TIME(0,56,0) -> 45664.661 | AB72: =(AA72-Z72)*84600/60 -> 54.833333 | AD72: =Z72-R72 -> 1.8895833 | AE72: 2 | AF72: =AE72-AD72 -> 0.11041667 | AG72: =AD72*24 -> 45.35 | AH72: =AG72-AI72 -> 12 | AI72: =((Z72 - R72) * 24) - (INT(Z72 - R72) * 12) -> 33.35 | AJ72: =I72/AI72 -> 4.6776612
A73: 45662.701 | B73: =TEXT(A73, "MMMM") -> January | D73: OMNK83VRR | E73: DJ | F73: ALIPA EREKU | G73: UBK 858R | H73: Bates Enterprises U Ltd | I73: 156 | J73: Z82073 | K73: OM | L73: 606 | M73: 576 | N73: =M73-L73 -> -30 | P73: =R73-TIME(0,43,0) -> 45662.747 | Q73: 45662.729 | R73: 45662.777 | S73: =(R73-Q73)*86000/60 -> 68.680556 | T73: =(R73-P73)*86000/60 -> 42.800926 | V73: 45664.331 | W73: =V73+TIME(0,167,0) -> 45664.447 | X73: =(W73-V73)*84600/60 -> 163.52083 | Z73: 45665.422 | AA73: 45665.462 | AB73: =(AA73-Z73)*84600/60 -> 55.8125 | AD73: =Z73-R73 -> 2.6451389 | AE73: 3 | AF73: =AE73-AD73 -> 0.35486111 | AG73: =AD73*24 -> 63.483333 | AH73: =AG73-AI73 -> 24 | AI73: =((Z73 - R73) * 24) - (INT(Z73 - R73) * 12) -> 39.483333 | AJ73: =I73/AI73 -> 3.9510342
A74: 45662.97 | B74: =TEXT(A74, "MMMM") -> January | D74: OM49I5JRR | E74: Manual | F74: ZIWA ABASI | G74: UBJ 420C | H74: Boniface Harera | I74: 156 | J74: F15681 | K74: OM | L74: 470 | M74: 465 | N74: =M74-L74 -> -5 | P74: 45663.489 | Q74: 45663.47 | R74: 45663.517 | S74: =(R74-Q74)*86000/60 -> 67.685185 | T74: =(R74-P74)*86000/60 -> 39.814815 | V74: 45664.517 | W74: =V74+TIME(0,167,0) -> 45664.633 | X74: =(W74-V74)*84600/60 -> 163.52083 | Z74: 45665.672 | AA74: 45665.706 | AB74: =(AA74-Z74)*84600/60 -> 47.979167 | AD74: =Z74-R74 -> 2.1548611 | AE74: 2 | AF74: =AE74-AD74 -> -0.15486111 | AG74: =AD74*24 -> 51.716667 | AH74: =AG74-AI74 -> 24 | AI74: =((Z74 - R74) * 24) - (INT(Z74 - R74) * 12) -> 27.716667 | AJ74: =I74/AI74 -> 5.6283824
A75: 45662.971 | B75: =TEXT(A75, "MMMM") -> January | D75: OMYOY87RR | E75: DJ | F75: SULAIMAN MUBIRU | G75: UBK 862R | H75: Kato Investment Ltd -Kagadi | I75: 156 | J75: A19879 | K75: OM | L75: 670 | M75: 622 | N75: =M75-L75 -> -48 | P75: =R75-TIME(0,41,0) -> 45662.951 | Q75: 45663.74 | R75: 45662.98 | S75: =(R75-Q75)*86000/60 -> -1089.9306 | T75: =(R75-P75)*86000/60 -> 40.810185 | V75: 45663.837 | W75: =V75+TIME(0,207,0) -> 45663.981 | X75: =(W75-V75)*84600/60 -> 202.6875 | Y75: space consquents | Z75: 45664.921 | AA75: 45664.96 | AB75: =(AA75-Z75)*84600/60 -> 55.8125 | AD75: =Z75-R75 -> 1.9409722 | AE75: 2 | AF75: =AE75-AD75 -> 0.059027778 | AG75: =AD75*24 -> 46.583333 | AH75: =AG75-AI75 -> 12 | AI75: =((Z75 - R75) * 24) - (INT(Z75 - R75) * 12) -> 34.583333 | AJ75: =I75/AI75 -> 4.5108434
A76: 45662.972 | B76: =TEXT(A76, "MMMM") -> January | D76: OMU06VORR | E76: DJ | F76: BYEKWASO TWAHA | G76: UBE 680K | H76: Kato Investment Ltd -Mityana | I76: 156 | J76: A19880 | K76: OM | L76: 690 | M76: =L76+2 -> 692 | N76: =M76-L76 -> 2 | P76: =R76-TIME(0,76,0) -> 45663.51 | Q76: 45663.816 | R76: 45663.563 | S76: =(R76-Q76)*86000/60 -> -362.31481 | T76: =(R76-P76)*86000/60 -> 75.648148 | U76: Pre-Trip inspection defect closure | V76: 45664.674 | W76: =V76+TIME(0,161,0) -> 45664.786 | X76: =(W76-V76)*84600/60 -> 157.64583 | Z76: 45665.406 | AA76: =Z76+TIME(0,58,0) -> 45665.447 | AB76: =(AA76-Z76)*84600/60 -> 56.791667 | AD76: =Z76-R76 -> 1.8430556 | AE76: 2 | AF76: =AE76-AD76 -> 0.15694444 | AG76: =AD76*24 -> 44.233333 | AH76: =AG76-AI76 -> 12 | AI76: =((Z76 - R76) * 24) - (INT(Z76 - R76) * 12) -> 32.233333 | AJ76: =I76/AI76 -> 4.8397104
A77: 45663 | B77: =TEXT(A77, "MMMM") -> January | D77: OM02L7T0 | E77: Manual | F77: Kakembo Masuud | G77: UBB 115P | H77: Boniface Harera | I77: 156 | J77: F15684 | K77: OM | L77: 470 | M77: =L77-1 -> 469 | N77: =M77-L77 -> -1 | P77: 45663.332 | Q77: 45663.312 | R77: 45663.36 | S77: =(R77-Q77)*86000/60 -> 67.685185 | T77: =(R77-P77)*86000/60 -> 39.814815 | V77: 45664.443 | W77: =V77+TIME(0,158,0) -> 45664.553 | X77: =(W77-V77)*84600/60 -> 154.70833 | Z77: 45665.612 | AA77: =Z77+TIME(0,58,0) -> 45665.652 | AB77: =(AA77-Z77)*84600/60 -> 56.791667 | AD77: =Z77-R77 -> 2.2520833 | AE77: 2 | AF77: =AE77-AD77 -> -0.25208333 | AG77: =AD77*24 -> 54.05 | AH77: =AG77-AI77 -> 24 | AI77: =((Z77 - R77) * 24) - (INT(Z77 - R77) * 12) -> 30.05 | AJ77: =I77/AI77 -> 5.1913478
A78: 45663 | B78: =TEXT(A78, "MMMM") -> January | D78: OM02L7T9 | E78: Manual | F78: Kakembo Masuud | G78: UBB 115P | H78: Kobusinge Steven-FPortal | I78: 156 | J78: Z82085 | K78: OM | L78: 390 | M78: =L78-2 -> 388 | N78: =M78-L78 -> -2 | P78: =R78-TIME(0,40,0) -> 45663.349 | Q78: 45663.312 | R78: 45663.376 | S78: =(R78-Q78)*86000/60 -> 91.574074 | T78: =(R78-P78)*86000/60 -> 39.814815 | V78: 45664.439 | W78: =V78+TIME(0,175,0) -> 45664.56 | X78: =(W78-V78)*84600/60 -> 171.35417 | Z78: 45665.469 | AA78: =Z78+TIME(0,59,0) -> 45665.51 | AB78: =(AA78-Z78)*84600/60 -> 57.770833 | AD78: =Z78-R78 -> 2.0925 | AE78: 2 | AF78: =AE78-AD78 -> -0.0925 | AG78: =AD78*24 -> 50.22 | AH78: =AG78-AI78 -> 24 | AI78: =((Z78 - R78) * 24) - (INT(Z78 - R78) * 12) -> 26.22 | AJ78: =I78/AI78 -> 5.9496568
A79: 45663.556 | B79: =TEXT(A79, "MMMM") -> January | D79: OMTGDUXRR | E79: DJ | F79: Tumusiime Robert | G79: UBJ 988D | H79: Rugoma Traders-Kanungu/Kihihi | I79: 153.6 | J79: F15682 | K79: OM | L79: 414 | M79: =L79-1 -> 413 | N79: =M79-L79 -> -1 | P79: =R79-TIME(0,40,0) -> 45663.62 | Q79: 45664.083 | R79: 45663.648 | S79: =(R79-Q79)*86000/60 -> -623.10185 | T79: =(R79-P79)*86000/60 -> 39.814815 | V79: 45664.512 | W79: =V79+TIME(0,171,0) -> 45664.631 | X79: =(W79-V79)*84600/60 -> 167.4375 | Z79: 45665.539 | AA79: 45665.599 | AB79: =(AA79-Z79)*84600/60 -> 84.208333 | AC79: loading delays | AD79: =Z79-R79 -> 1.8909722 | AE79: 2 | AF79: =AE79-AD79 -> 0.10902778 | AG79: =AD79*24 -> 45.383333 | AH79: =AG79-AI79 -> 12 | AI79: =((Z79 - R79) * 24) - (INT(Z79 - R79) * 12) -> 33.383333 | AJ79: =I79/AI79 -> 4.6010984
A80: 45663.557 | B80: =TEXT(A80, "MMMM") -> January | D80: OM4O141RR | E80: DJ | F80: Kilabila Ismail | G80: UBE 419T | H80: Agaba Services | I80: 153.6 | J80: F15683 | K80: OM | L80: 302 | M80: 295 | N80: =M80-L80 -> -7 | P80: =R80-TIME(0,39,0) -> 45663.784 | Q80: 45664.177 | R80: 45663.811 | S80: =(R80-Q80)*86000/60 -> -524.56019 | T80: =(R80-P80)*86000/60 -> 38.819444 | V80: 45664.489 | W80: =V80+TIME(0,167,0) -> 45664.605 | X80: =(W80-V80)*84600/60 -> 163.52083 | Z80: 45664.751 | AA80: 45664.79 | AB80: =(AA80-Z80)*84600/60 -> 54.833333 | AD80: =Z80-R80 -> 0.93958333 | AE80: 2 | AF80: =AE80-AD80 -> 1.0604167 | AG80: =AD80*24 -> 22.55 | AH80: =AG80-AI80 -> 0 | AI80: =((Z80 - R80) * 24) - (INT(Z80 - R80) * 12) -> 22.55 | AJ80: =I80/AI80 -> 6.8115299
A81: 45663.591 | B81: =TEXT(A81, "MMMM") -> January | D81: OM76ZVYRR | E81: Manual | F81: Angello Lumala | G81: UAV 051U | H81: KATO INVESTMENTS LIMITED-MASAK | I81: 153.6 | J81: F15685 | K81: OM | L81: 340 | M81: 328 | N81: =M81-L81 -> -12 | P81: =R81-TIME(0,41,0) -> 45664.112 | Q81: 45664.091 | R81: 45664.141 | S81: =(R81-Q81)*86000/60 -> 71.666667 | T81: =(R81-P81)*86000/60 -> 40.810185 | V81: 45664.275 | W81: =V81+TIME(0,161,0) -> 45664.387 | X81: =(W81-V81)*84600/60 -> 157.64583 | Z81: 45665.078 | AA81: =Z81+TIME(0,59,0) -> 45665.119 | AB81: =(AA81-Z81)*84600/60 -> 57.770833 | AD81: =Z81-R81 -> 0.93680556 | AE81: 2 | AF81: =AE81-AD81 -> 1.0631944 | AG81: =AD81*24 -> 22.483333 | AH81: =AG81-AI81 -> 0 | AI81: =((Z81 - R81) * 24) - (INT(Z81 - R81) * 12) -> 22.483333 | AJ81: =I81/AI81 -> 6.8317272
A82: 45663.759 | B82: =TEXT(A82, "MMMM") -> January | D82: OMYKJ8LRR | E82: DJ | F82: Jacob Oneka | G82: UBE 422T | H82: KATO INVESTMENTS LTD-KATIKARA | I82: 153.6 | J82: A19895 | K82: OM | L82: 790 | M82: =L82+2 -> 792 | N82: =M82-L82 -> 2 | P82: =R82-TIME(0,63,0) -> 45663.724 | Q82: 45663.833 | R82: 45663.768 | S82: =(R82-Q82)*86000/60 -> -93.564815 | T82: =(R82-P82)*86000/60 -> 62.708333 | U82: Jam at the weigh bridge | V82: 45664.768 | W82: =V82+TIME(0,161,0) -> 45664.88 | X82: =(W82-V82)*84600/60 -> 157.64583 | Z82: 45666.41 | AA82: =Z82+TIME(0,57,0) -> 45666.45 | AB82: =(AA82-Z82)*84600/60 -> 55.8125 | AD82: =Z82-R82 -> 2.6423611 | AE82: 3 | AF82: =AE82-AD82 -> 0.35763889 | AG82: =AD82*24 -> 63.416667 | AH82: =AG82-AI82 -> 24 | AI82: =((Z82 - R82) * 24) - (INT(Z82 - R82) * 12) -> 39.416667 | AJ82: =I82/AI82 -> 3.8968288
A83: 45663.76 | B83: =TEXT(A83, "MMMM") -> January | D83: OMSZNXIRR | E83: DJ | F83: Stephen Musoke | G83: UBJ 375N | H83: KATO INVESTMENTS LTD- KALISIZO | I83: 153.6 | J83: F15686 | K83: OM | L83: 350 | M83: 343 | N83: =M83-L83 -> -7 | P83: =R83-TIME(0,40,0) -> 45664.737 | Q83: 45664.155 | R83: 45664.765 | S83: =(R83-Q83)*86000/60 -> 874.93056 | T83: =(R83-P83)*86000/60 -> 39.814815 | V83: 45665.467 | W83: =V83+TIME(0,360,0) -> 45665.717 | X83: =(W83-V83)*84600/60 -> 352.5 | Y83: slept at the RD and offloaded the next day | Z83: 45666.431 | AA83: 45666.469 | AB83: =(AA83-Z83)*84600/60 -> 54.833333 | AD83: =Z83-R83 -> 1.6652778 | AE83: 2 | AF83: =AE83-AD83 -> 0.33472222 | AG83: =AD83*24 -> 39.966667 | AH83: =AG83-AI83 -> 12 | AI83: =((Z83 - R83) * 24) - (INT(Z83 - R83) * 12) -> 27.966667 | AJ83: =I83/AI83 -> 5.4922527
A84: 45663.761 | B84: =TEXT(A84, "MMMM") -> January | D84: OMRF7ELRR | E84: Manual | F84: Godwin Niwensiima | G84: UAR 731Q | H84: KATO INVESTMENTS LIMITED-MASAK | I84: 153.6 | J84: F15687 | K84: OM | L84: 340 | M84: 328 | N84: =M84-L84 -> -12 | P84: 45664.332 | Q84: 45664.313 | R84: 45664.36 | S84: =(R84-Q84)*86000/60 -> 67.685185 | T84: =(R84-P84)*86000/60 -> 39.814815 | V84: 45664.494 | W84: =V84+TIME(0,167,0) -> 45664.61 | X84: =(W84-V84)*84600/60 -> 163.52083 | Z84: 45665.308 | AA84: 45665.345 | AB84: =(AA84-Z84)*84600/60 -> 51.895833 | AD84: =Z84-R84 -> 0.94791667 | AE84: 2 | AF84: =AE84-AD84 -> 1.0520833 | AG84: =AD84*24 -> 22.75 | AH84: =AG84-AI84 -> 0 | AI84: =((Z84 - R84) * 24) - (INT(Z84 - R84) * 12) -> 22.75 | AJ84: =I84/AI84 -> 6.7516484
A85: 45663.762 | B85: =TEXT(A85, "MMMM") -> January | D85: OMLA1GERR | E85: Manual | F85: Hamudi Sesanga | G85: UAT 351G | H85: KATO INVESTMENTS LIMITED-MASAK | I85: 153.6 | J85: F15688 | K85: OM | L85: 340 | M85: =L85-1 -> 339 | N85: =M85-L85 -> -1 | P85: =R85-TIME(0,44,0) -> 45664.329 | Q85: 45664.313 | R85: 45664.36 | S85: =(R85-Q85)*86000/60 -> 67.685185 | T85: =(R85-P85)*86000/60 -> 43.796296 | V85: 45664.494 | W85: =V85+TIME(0,153,0) -> 45664.6 | X85: =(W85-V85)*84600/60 -> 149.8125 | Z85: 45665.311 | AA85: 45665.35 | AB85: =(AA85-Z85)*84600/60 -> 54.833333 | AD85: =Z85-R85 -> 0.95069444 | AE85: 2 | AF85: =AE85-AD85 -> 1.0493056 | AG85: =AD85*24 -> 22.816667 | AH85: =AG85-AI85 -> 0 | AI85: =((Z85 - R85) * 24) - (INT(Z85 - R85) * 12) -> 22.816667 | AJ85: =I85/AI85 -> 6.7319211
A86: 45663.933 | B86: =TEXT(A86, "MMMM") -> January | D86: OMXCAB3RR | E86: Manual | F86: Nakalya John | G86: UBM 648D | H86: Kabaco U Ltd | I86: 156 | J86: Z82086 | K86: OM | L86: 320 | M86: 323 | N86: =M86-L86 -> 3 | P86: =R86-TIME(0,57,0) -> 45664.451 | Q86: 45664.433 | R86: 45664.49 | S86: =(R86-Q86)*86000/60 -> 82.615741 | T86: =(R86-P86)*86000/60 -> 56.736111 | U86: Reconciling stock count delays | V86: 45664.74 | W86: =V86+TIME(0,175,0) -> 45664.862 | X86: =(W86-V86)*84600/60 -> 171.35417 | Z86: 45665.812 | AA86: 45665.851 | AB86: =(AA86-Z86)*84600/60 -> 54.833333 | AD86: =Z86-R86 -> 1.3222222 | AE86: 2 | AF86: =AE86-AD86 -> 0.67777778 | AG86: =AD86*24 -> 31.733333 | AH86: =AG86-AI86 -> 12 | AI86: =((Z86 - R86) * 24) - (INT(Z86 - R86) * 12) -> 19.733333 | AJ86: =I86/AI86 -> 7.9054054
A87: 45663.961 | B87: =TEXT(A87, "MMMM") -> January | D87: OMZ2EAARR | E87: DJ | F87: Bisaso Ronald | G87: UBK 875R | H87: Rugoma Traders-Kanungu/Kihihi | I87: 153.6 | J87: F15689 | K87: OM | L87: 414 | M87: =L87-1 -> 413 | N87: =M87-L87 -> -1 | P87: =R87-TIME(0,53,0) -> 45665.424 | Q87: 45664.333 | R87: 45665.461 | S87: =(R87-Q87)*86000/60 -> 1616.4815 | T87: =(R87-P87)*86000/60 -> 52.75463 | U87: Unplanned Training | V87: 45665.732 | W87: =V87+TIME(0,167,0) -> 45665.848 | X87: =(W87-V87)*84600/60 -> 163.52083 | Z87: 45667.422 | AA87: 45667.46 | AB87: =(AA87-Z87)*84600/60 -> 54.833333 | AD87: =Z87-R87 -> 1.9604167 | AE87: 2 | AF87: =AE87-AD87 -> 0.039583333 | AG87: =AD87*24 -> 47.05 | AH87: =AG87-AI87 -> 12 | AI87: =((Z87 - R87) * 24) - (INT(Z87 - R87) * 12) -> 35.05 | AJ87: =I87/AI87 -> 4.382311
A88: 45664 | B88: =TEXT(A88, "MMMM") -> January | D88: OM02L8B9 | E88: Manual | G88: UBP 311H | H88: Sawan Distributors Ltd-Kayabwe | I88: 156 | J88: A19916 | K88: OM | L88: 382 | M88: =L88-1 -> 381 | N88: =M88-L88 -> -1 | P88: =R88-TIME(0,43,0) -> 45664.333 | Q88: 45664.312 | R88: 45664.362 | S88: =(R88-Q88)*86000/60 -> 71.666667 | T88: =(R88-P88)*86000/60 -> 42.800926 | V88: 45665.487 | W88: =V88+TIME(0,153,0) -> 45665.594 | X88: =(W88-V88)*84600/60 -> 149.8125 | Z88: 45666.581 | AA88: =Z88+TIME(0,59,0) -> 45666.622 | AB88: =(AA88-Z88)*84600/60 -> 57.770833 | AD88: =Z88-R88 -> 2.21875 | AE88: 2 | AF88: =AE88-AD88 -> -0.21875 | AG88: =AD88*24 -> 53.25 | AH88: =AG88-AI88 -> 24 | AI88: =((Z88 - R88) * 24) - (INT(Z88 - R88) * 12) -> 29.25 | AJ88: =I88/AI88 -> 5.3333333
A89: 45664 | B89: =TEXT(A89, "MMMM") -> January | D89: OM02L801 | E89: Manual | G89: UBK 866R | H89: Kato Investment Ltd -Kagadi | I89: 156 | J89: A19901 | K89: OM | L89: 670 | M89: 612 | N89: =M89-L89 -> -58 | P89: =R89-TIME(0,39,0) -> 45664.339 | Q89: 45664.312 | R89: 45664.366 | S89: =(R89-Q89)*86000/60 -> 76.643519 | T89: =(R89-P89)*86000/60 -> 38.819444 | V89: 45665.428 | W89: =V89+TIME(0,267,0) -> 45665.614 | X89: =(W89-V89)*84600/60 -> 261.4375 | Y89: Waited for empties from trade | Z89: 45666.408 | AA89: =Z89+TIME(0,58,0) -> 45666.448 | AB89: =(AA89-Z89)*84600/60 -> 56.791667 | AD89: =Z89-R89 -> 2.0420278 | AE89: 2 | AF89: =AE89-AD89 -> -0.042027778 | AG89: =AD89*24 -> 49.008667 | AH89: =AG89-AI89 -> 24 | AI89: =((Z89 - R89) * 24) - (INT(Z89 - R89) * 12) -> 25.008667 | AJ89: =I89/AI89 -> 6.2378375
A90: 45664 | B90: =TEXT(A90, "MMMM") -> January | D90: OM02L87X | E90: Manual | G90: UBP 311H | H90: Boniface Harera | I90: 156 | J90: F15690 | K90: OM | L90: 470 | M90: 465 | N90: =M90-L90 -> -5 | P90: =R90-TIME(0,39,0) -> 45664.338 | Q90: 45664.312 | R90: 45664.365 | S90: =(R90-Q90)*86000/60 -> 75.648148 | T90: =(R90-P90)*86000/60 -> 38.819444 | V90: 45665.428 | W90: =V90+TIME(0,307,0) -> 45665.641 | X90: =(W90-V90)*84600/60 -> 300.60417 | Y90: Reached late and offloaded the next day | Z90: 45666.578 | AA90: 45666.617 | AB90: =(AA90-Z90)*84600/60 -> 54.833333 | AD90: =Z90-R90 -> 2.2125 | AE90: 2 | AF90: =AE90-AD90 -> -0.2125 | AG90: =AD90*24 -> 53.1 | AH90: =AG90-AI90 -> 24 | AI90: =((Z90 - R90) * 24) - (INT(Z90 - R90) * 12) -> 29.1 | AJ90: =I90/AI90 -> 5.3608247
A91: 45664 | B91: =TEXT(A91, "MMMM") -> January | D91: OM02L80B | E91: Manual | G91: UBK 866R | H91: Kabaco U Ltd | I91: 156 | J91: Z82087 | K91: OM | L91: 320 | M91: 321 | N91: =M91-L91 -> 1 | P91: 45664.332 | Q91: 45664.312 | R91: 45664.36 | S91: =(R91-Q91)*86000/60 -> 67.685185 | T91: =(R91-P91)*86000/60 -> 39.814815 | V91: 45664.61 | W91: =V91+TIME(0,149,0) -> 45664.713 | X91: =(W91-V91)*84600/60 -> 145.89583 | Z91: 45665.495 | AA91: 45665.534 | AB91: =(AA91-Z91)*84600/60 -> 54.833333 | AD91: =Z91-R91 -> 1.1355556 | AE91: 2 | AF91: =AE91-AD91 -> 0.86444444 | AG91: =AD91*24 -> 27.253333 | AH91: =AG91-AI91 -> 12 | AI91: =((Z91 - R91) * 24) - (INT(Z91 - R91) * 12) -> 15.253333 | AJ91: =I91/AI91 -> 10.227273
A92: 45664 | B92: =TEXT(A92, "MMMM") -> January | D92: OM02L8AK | E92: Manual | F92: Ekwalikwa Yusuf | G92: UBP 311H | H92: Ntale and Sons Ltd-Kakiri | I92: 155.1 | J92: A19913 | K92: OM | L92: 620 | M92: 602 | N92: =M92-L92 -> -18 | P92: =R92-TIME(0,77,0) -> 45664.32 | Q92: 45664.312 | R92: 45664.374 | S92: =(R92-Q92)*86000/60 -> 87.592593 | T92: =(R92-P92)*86000/60 -> 76.643519 | V92: 45665.353 | W92: =V92+TIME(0,167,0) -> 45665.469 | X92: =(W92-V92)*84600/60 -> 163.52083 | Z92: 45666.418 | AA92: =Z92+TIME(0,58,0) -> 45666.459 | AB92: =(AA92-Z92)*84600/60 -> 56.791667 | AD92: =Z92-R92 -> 2.0448611 | AE92: 3 | AF92: =AE92-AD92 -> 0.95513889 | AG92: =AD92*24 -> 49.076667 | AH92: =AG92-AI92 -> 24 | AI92: =((Z92 - R92) * 24) - (INT(Z92 - R92) * 12) -> 25.076667 | AJ92: =I92/AI92 -> 6.1850326
A93: 45664 | B93: =TEXT(A93, "MMMM") -> January | D93: OM02L807 | E93: Manual | G93: UBK 866R | H93: Kato Investments Ltd- Kyegegwa | I93: 156 | J93: A19902 | K93: OM | L93: 600 | M93: 572 | N93: =M93-L93 -> -28 | P93: =R93-TIME(0,49,0) -> 45664.342 | Q93: 45664.312 | R93: 45664.376 | S93: =(R93-Q93)*86000/60 -> 91.574074 | T93: =(R93-P93)*86000/60 -> 48.773148 | U93: DJ failures | V93: 45665.439 | W93: =V93+TIME(0,175,0) -> 45665.56 | X93: =(W93-V93)*84600/60 -> 171.35417 | Z93: 45666.477 | AA93: =Z93+TIME(0,57,0) -> 45666.517 | AB93: =(AA93-Z93)*84600/60 -> 55.8125 | AD93: =Z93-R93 -> 2.1008333 | AE93: 2 | AF93: =AE93-AD93 -> -0.10083333 | AG93: =AD93*24 -> 50.42 | AH93: =AG93-AI93 -> 24 | AI93: =((Z93 - R93) * 24) - (INT(Z93 - R93) * 12) -> 26.42 | AJ93: =I93/AI93 -> 5.9046177
A94: 45664.53 | B94: =TEXT(A94, "MMMM") -> January | D94: OM7OPDRRR | E94: DJ | F94: NASASIRA STEPHENE | G94: UBK 882R | H94: Kato Investment Ltd -Mityana | I94: 187.2 | J94: A19903 | K94: OM | L94: 690 | M94: =L94+2 -> 692 | N94: =M94-L94 -> 2 | P94: =R94-TIME(0,43,0) -> 45664.501 | Q94: 45664.566 | R94: 45664.531 | S94: =(R94-Q94)*86000/60 -> -50.763889 | T94: =(R94-P94)*86000/60 -> 42.800926 | V94: 45665.539 | W94: =V94+TIME(0,367,0) -> 45665.794 | X94: =(W94-V94)*84600/60 -> 359.35417 | Y94: Waited for empties from trade | Z94: 45666.451 | AA94: 45666.49 | AB94: =(AA94-Z94)*84600/60 -> 54.833333 | AD94: =Z94-R94 -> 1.9201389 | AE94: 3 | AF94: =AE94-AD94 -> 1.0798611 | AG94: =AD94*24 -> 46.083333 | AH94: =AG94-AI94 -> 12 | AI94: =((Z94 - R94) * 24) - (INT(Z94 - R94) * 12) -> 34.083333 | AJ94: =I94/AI94 -> 5.4924205
A95: 45664.541 | B95: =TEXT(A95, "MMMM") -> January | D95: OMCGJHRRR | E95: DJ | F95: Abel Mark naffa | G95: UBJ 415C | H95: Kabaco U Ltd-Mbarara | I95: 153.6 | J95: Z82089 | K95: OM | L95: 20 | M95: 12 | N95: =M95-L95 -> -8 | P95: =R95-TIME(0,41,0) -> 45664.803 | Q95: 45664.625 | R95: 45664.832 | S95: =(R95-Q95)*86000/60 -> 296.62037 | T95: =(R95-P95)*86000/60 -> 40.810185 | V95: 45665.463 | W95: =V95+TIME(0,153,0) -> 45665.569 | X95: =(W95-V95)*84600/60 -> 149.8125 | Z95: 45665.601 | AA95: =Z95+TIME(0,58,0) -> 45665.642 | AB95: =(AA95-Z95)*84600/60 -> 56.791667 | AD95: =Z95-R95 -> 0.76944444 | AE95: 2 | AF95: =AE95-AD95 -> 1.2305556 | AG95: =AD95*24 -> 18.466667 | AH95: =AG95-AI95 -> 0 | AI95: =((Z95 - R95) * 24) - (INT(Z95 - R95) * 12) -> 18.466667 | AJ95: =I95/AI95 -> 8.3176895
A96: 45664.787 | B96: =TEXT(A96, "MMMM") -> January | D96: OMFEHYMRR | E96: DJ | F96: Konge Husein | G96: UBJ 707D | H96: Kabaco U Ltd | I96: 153.6 | J96: Z82091 | K96: OM | L96: 320 | M96: 317 | N96: =M96-L96 -> -3 | P96: =R96-TIME(0,43,0) -> 45664.785 | Q96: 45665.099 | R96: 45664.815 | S96: =(R96-Q96)*86000/60 -> -407.10648 | T96: =(R96-P96)*86000/60 -> 42.800926 | V96: 45665.457 | W96: =V96+TIME(0,153,0) -> 45665.563 | X96: =(W96-V96)*84600/60 -> 149.8125 | Z96: 45667.327 | AA96: 45667.366 | AB96: =(AA96-Z96)*84600/60 -> 54.833333 | AD96: =Z96-R96 -> 2.5125 | AE96: 2 | AF96: =AE96-AD96 -> -0.5125 | AG96: =AD96*24 -> 60.3 | AH96: =AG96-AI96 -> 24 | AI96: =((Z96 - R96) * 24) - (INT(Z96 - R96) * 12) -> 36.3 | AJ96: =I96/AI96 -> 4.231405
A97: 45664.788 | B97: =TEXT(A97, "MMMM") -> January | D97: OMIFRI4RR | E97: DJ | F97: Benon Ssempijja | G97: UAY 526V | H97: Agaba Services | I97: 153.6 | J97: F15691 | K97: OM | L97: 302 | M97: 294 | N97: =M97-L97 -> -8 | P97: =R97-TIME(0,39,0) -> 45665.387 | Q97: 45665.177 | R97: 45665.415 | S97: =(R97-Q97)*86000/60 -> 340.41667 | T97: =(R97-P97)*86000/60 -> 38.819444 | V97: 45665.645 | W97: =V97+TIME(0,153,0) -> 45665.751 | X97: =(W97-V97)*84600/60 -> 149.8125 | Z97: 45666.374 | AA97: =Z97+TIME(0,58,0) -> 45666.414 | AB97: =(AA97-Z97)*84600/60 -> 56.791667 | AD97: =Z97-R97 -> 0.95902778 | AE97: 2 | AF97: =AE97-AD97 -> 1.0409722 | AG97: =AD97*24 -> 23.016667 | AH97: =AG97-AI97 -> 0 | AI97: =((Z97 - R97) * 24) - (INT(Z97 - R97) * 12) -> 23.016667 | AJ97: =I97/AI97 -> 6.6734251
A98: 45664.789 | B98: =TEXT(A98, "MMMM") -> January | D98: OM65I70RR | E98: DJ | F98: Kilabila Ismail | G98: UBE 419T | H98: Kabaco U Ltd-Mbarara | I98: 153.6 | J98: Z82092 | K98: OM | L98: 20 | M98: 14 | N98: =M98-L98 -> -6 | P98: =R98-TIME(0,40,0) -> 45664.777 | Q98: 45665.321 | R98: 45664.805 | S98: =(R98-Q98)*86000/60 -> -739.56019 | T98: =(R98-P98)*86000/60 -> 39.814815 | V98: 45664.839 | W98: =V98+TIME(0,153,0) -> 45664.945 | X98: =(W98-V98)*84600/60 -> 149.8125 | Z98: 45665.652 | AA98: =Z98+TIME(0,59,0) -> 45665.693 | AB98: =(AA98-Z98)*84600/60 -> 57.770833 | AD98: =Z98-R98 -> 0.84722222 | AE98: 2 | AF98: =AE98-AD98 -> 1.1527778 | AG98: =AD98*24 -> 20.333333 | AH98: =AG98-AI98 -> 0 | AI98: =((Z98 - R98) * 24) - (INT(Z98 - R98) * 12) -> 20.333333 | AJ98: =I98/AI98 -> 7.5540984
A99: 45664.794 | B99: =TEXT(A99, "MMMM") -> January | D99: OMBC2B0RR | E99: DJ | F99: SENTONG DAVID | G99: UBP 298H | H99: Rugoma Traders-Rukungiri | I99: 156 | J99: Z82093 | K99: OM | L99: 256 | M99: =L99-1 -> 255 | N99: =M99-L99 -> -1 | P99: =R99-TIME(0,43,0) -> 45665.406 | Q99: 45665.169 | R99: 45665.436 | S99: =(R99-Q99)*86000/60 -> 382.22222 | T99: =(R99-P99)*86000/60 -> 42.800926 | V99: 45665.714 | W99: =V99+TIME(0,161,0) -> 45665.826 | X99: =(W99-V99)*84600/60 -> 157.64583 | Z99: 45666.699 | AA99: =Z99+TIME(0,58,0) -> 45666.739 | AB99: =(AA99-Z99)*84600/60 -> 56.791667 | AD99: =Z99-R99 -> 1.2625 | AE99: 2 | AF99: =AE99-AD99 -> 0.7375 | AG99: =AD99*24 -> 30.3 | AH99: =AG99-AI99 -> 12 | AI99: =((Z99 - R99) * 24) - (INT(Z99 - R99) * 12) -> 18.3 | AJ99: =I99/AI99 -> 8.5245902
A100: 45664.826 | B100: =TEXT(A100, "MMMM") -> January | D100: OM8ZA87RR | E100: DJ | F100: Isaac Tumuhimbise | G100: UBE 287X | H100: KATO INVESTMENTS LIMITED-MASAK | I100: 153.6 | J100: F15692 | K100: OM | L100: 340 | M100: 154 | N100: =M100-L100 -> -186 | P100: =R100-TIME(0,43,0) -> 45665.286 | Q100: 45665.176 | R100: 45665.316 | S100: =(R100-Q100)*86000/60 -> 200.06944 | T100: =(R100-P100)*86000/60 -> 42.800926 | V100: 45665.441 | W100: =V100+TIME(0,167,0) -> 45665.557 | X100: =(W100-V100)*84600/60 -> 163.52083 | Z100: 45666.359 | AA100: 45666.419 | AB100: =(AA100-Z100)*84600/60 -> 85.1875 | AC100: Traffic at gate | AD100: =Z100-R100 -> 1.0430556 | AE100: 2 | AF100: =AE100-AD100 -> 0.95694444 | AG100: =AD100*24 -> 25.033333 | AH100: =AG100-AI100 -> 12 | AI100: =((Z100 - R100) * 24) - (INT(Z100 - R100) * 12) -> 13.033333 | AJ100: =I100/AI100 -> 11.785166
...

Sheet Customer Master Data
A1: Customer Name | B1: Customer # | C1: Customer Name2 | D1: Customer Type | E1: Customer Contact Name | F1: Contact Role | G1: Contact Number 1 | H1: Contact no 2 | I1: Contact no 3 | J1: E-mail Adress | K1: Street | L1: Geography | M1: Latitude | N1: Latitude3 | O1: Call Type | P1: Call Frequency 1 | Q1: # DD | R1: Mon | S1: Tue | T1: Wed | U1: Thu | V1: Fri | W1: Sat | X1: Sun | Y1: Max Truck Capacity | Z1: Time Window | AA1: CIC Agent | AB1: Sales Rep / Distributor Specialist | AC1: Delivery Points | AD1: Max Stock Capacity at outlet cases | AE1: 12 month sales volume HL | AF1: 12 months # of deliveries | AG1: 12 Month # of FBR's | AH1: Credit Limit | AI1: Mon4 | AJ1: Tue5 | AK1: Wed6 | AL1: Thu7 | AM1: Fri8 | AN1: Sat9 | AO1: Sun10 | AP1: DEL DAYS COMBINED | AQ1: Budgeted KMs | AR1: Budget Cases | AS1: Lane allocation | AT1: Rate | AU1: Budget cost | AV1: Budget Net Revenue | AW1: Capacity Occupation | AX1: Budget: Cases /km | AY1: Cost/case UGX | AZ1: Net Revenue% Contribution | BA1: Cost/case Rank | BB1: Volume Contribution | BC1: Location type | BD1: Main catergory | BE1: Distribution Segmentation | BF1: Clustering | BG1: Volume % | BH1: NetReve Growth | BI1: Cost to deliver | BJ1: CO HL | BK1: OTIF | BL1: NPS | BM1: RMD | BN1: Points
A2: AGABA SERVICES | B2: BAGA011 | C2: BYARUGABA MOSES | D2: Distribution Centre | E2: BYARUGABA MOSES | F2: OWNER | G2: 777664482 | H2: 777664482 | I2: 777664482 | J2: kalvomark@yahoo.com | K2: KABALE | L2: KABALE | M2: -1.2994117 | N2: 29.998562 | O2: T | P2: Mon-Sun | Q2: 7 | R2: X | S2: X | T2: X | U2: X | V2: X | W2: X | X2: X | Y2: 20 | Z2: 0800-1700 | AA2: Samuel Kenneth Ssekajja | AB2: Samuel Kenneth Ssekajja | AC2: 1 | AD2: 50000 | AE2: 43087 | AF2: 298 | AG2: 0 | AH2: 1904117805 | AI2: Mon | AJ2: Tue | AK2: Wed | AL2: Thu | AM2: Fri | AN2: Sat | AO2: Sun | AP2: Mon Tue Wed Thu Fri Sat Sun | AQ2: 302 | AR2: 402290 | AS2: Own | AT2: 5349 | AU2: 293057907 | AV2: 12619053999 | AW2: 145 | AX2: 4 | AY2: 728 | AZ2: 0.05 | BA2: 7 | BB2: 0.047 | BC2: Semi Urban | BD2: Value | BE2: Semi Urban Value | BF2: Winner | BG2: 3 | BH2: 3 | BI2: 4 | BJ2: 4 | BK2: 0.0019 | BL2: 92 | BM2: 5 | BN2: 3.5
A3: BATES BUNDIBUGYO | B3: BBAT035 | C3: TIMOTHY BAGUMA | D3: Distributor CENTER | E3: TIMOTHY BAGUMA | F3: OWNER | G3: 772394539 | H3: 772394539 | I3: 772394539 | J3: batesenterprises@gmail.com | K3: BUNDIBUGYO | L3: BUNDIBUGYO | M3: 0.71131167 | N3: 30.062473 | O3: T | P3: Mon-Sun | Q3: 7 | R3: X | S3: X | T3: X | U3: X | V3: X | W3: X | X3: X | Y3: 20 | Z3: 0800-1700 | AA3: Steven R. Bazungu | AB3: Steven R. Bazungu | AC3: 1 | AD3: 12000 | AE3: 9258 | AF3: 65 | AG3: 0 | AH3: 0 | AI3: Mon | AJ3: Tue | AK3: Wed | AL3: Thu | AM3: Fri | AN3: Sat | AO3: Sun | AP3: Mon Tue Wed Thu Fri Sat Sun | AQ3: 464 | AR3: 87324 | AS3: 3PL | AT3: 7000 | AU3: 200132831 | AV3: 2769003228 | AW3: 143.1 | AX3: 3 | AY3: 2292 | AZ3: 0.01 | BA3: 16 | BB3: 0.01 | BC3: Rural | BD3: Core | BE3: Rural Core | BF3: Basic | BG3: 2 | BH3: 2 | BI3: 3 | BJ3: 3 | BK3: 0.0216 | BM3: 5 | BN3: 2.5
A4: BATES NTOROKO | B4: BBAT036 | C4: TIMOTHY BAGUMA | D4: Distributor CENTER | E4: TIMOTHY BAGUMA | F4: MANAGER | G4: 772394539 | H4: 772394539 | I4: 772394539 | J4: batesenterprises@gmail.com | K4: NTOROKO | L4: NTOROKO | M4: 0.91969842 | N4: 30.187996 | O4: T | P4: Mon-Sun | Q4: 7 | R4: X | S4: X | T4: X | U4: X | V4: X | W4: X | X4: X | Y4: 20 | Z4: 0800-1700 | AA4: Steven R. Bazungu | AB4: Steven R. Bazungu | AC4: 1 | AD4: 5000 | AE4: 10104 | AF4: 73 | AG4: 0 | AH4: 0 | AI4: Mon | AJ4: Tue | AK4: Wed | AL4: Thu | AM4: Fri | AN4: Sat | AO4: Sun | AP4: Mon Tue Wed Thu Fri Sat Sun | AQ4: 442 | AR4: 97944 | AS4: 3PL | AT4: 7000 | AU4: 235645554 | AV4: 3133122476 | AW4: 139 | AX4: 3 | AY4: 2406 | AZ4: 0.01 | BA4: 18 | BB4: 0.011 | BC4: Rural | BD4: Core | BE4: Rural Core | BF4: Basic | BG4: 2 | BH4: 2 | BI4: 3 | BJ4: 1 | BK4: 0.0002 | BM4: 5 | BN4: 2.17
A5: DE'PLACE INVESTMENT | B5: NDE 001 | C5: BINGI JULIUS | D5: Distribution Centre | E5: BINGI JULIUS | F5: OWNER | G5: 772220243 | H5: 772220243 | I5: 772220243 | J5: deplaceinvestmentltd@yahoo.com | K5: HOIMA | L5: HOIMA | M5: 1.426095 | N5: 31.348788 | O5: T | P5: Mon-Sun | Q5: 7 | R5: X | S5: X | T5: X | U5: X | V5: X | W5: X | X5: X | Y5: 20 | Z5: 0800-1700 | AA5: Gerald Mugisa | AB5: Steven R. Bazungu | AC5: 1 | AD5: 30000 | AE5: 50377 | AF5: 366 | AG5: 0 | AH5: 1757414453 | AI5: Mon | AJ5: Tue | AK5: Wed | AL5: Thu | AM5: Fri | AN5: Sat | AO5: Sun | AP5: Mon Tue Wed Thu Fri Sat Sun | AQ5: 314 | AR5: 494552 | AS5: 3PL | AT5: 6340 | AU5: 1463118903 | AV5: 15012580218 | AW5: 138 | AX5: 2 | AY5: 2958 | AZ5: 0.06 | BA5: 23 | BB5: 0.055 | BC5: Urban | BD5: Core | BE5: Urban Core | BF5: Low | BG5: 4 | BH5: 4 | BI5: 2 | BJ5: 1 | BK5: 0.0015 | BL5: -18 | BM5: 5 | BN5: -0.29
A6: HARERA KISORO | B6: NBON002 | C6: HARERA | D6: Distribution Centre | E6: HARERA | F6: MANAGER | G6: 392960091 | H6: 702454399 | I6: 702454399 | J6: hareraboniface@yahoo.com | K6: KISORO | L6: KISORO | M6: -1.2808083 | N6: 29.692868 | O6: T | P6: Mon-Sun | Q6: 7 | R6: X | S6: X | T6: X | U6: X | V6: X | W6: X | X6: X | Y6: 20 | Z6: 0800-1700 | AA6: Samuel Kenneth Ssekajja | AB6: Steven R. Bazungu | AC6: 1 | AD6: 20000 | AE6: 35603 | AF6: 255 | AG6: 0 | AH6: 1390823982 | AI6: Mon | AJ6: Tue | AK6: Wed | AL6: Thu | AM6: Fri | AN6: Sat | AO6: Sun | AP6: Mon Tue Wed Thu Fri Sat Sun | AQ6: 380 | AR6: 344088 | AS6: 3PL | AT6: 7000 | AU6: 799303852 | AV6: 10734224767 | AW6: 139.7 | AX6: 3 | AY6: 2323 | AZ6: 0.04 | BA6: 17 | BB6: 0.039 | BC6: Semi Urban | BD6: Value | BE6: Semi Urban Value | BF6: Winner | BG6: 3 | BH6: 3 | BI6: 3 | BJ6: 1 | BK6: 0.0049 | BL6: 96 | BM6: 5 | BN6: 15.86
A7: KABACO KASESE | B7: BKAB002 | C7: CHARITY TUSIIME | D7: Distribution Centre | E7: CHARITY TUSIIME | F7: MANAGER | G7: 772816012 | H7: 772816012 | I7: 772816012 | J7: kabacougltd@yahoo.com | K7: KASESE | L7: KASESE | M7: 0.17510333 | N7: 30.079502 | O7: T | P7: Mon-Sun | Q7: 7 | R7: X | S7: X | T7: X | U7: X | V7: X | W7: X | X7: X | Y7: 20 | Z7: 0800-1700 | AA7: Steven R. Bazungu | AB7: Steven R. Bazungu | AC7: 1 | AD7: 45000 | AE7: 46190 | AF7: 323 | AG7: 0 | AH7: 1719981262 | AI7: Mon | AJ7: Tue | AK7: Wed | AL7: Thu | AM7: Fri | AN7: Sat | AO7: Sun | AP7: Mon Tue Wed Thu Fri Sat Sun | AQ7: 298 | AR7: 436684 | AS7: 3PL | AT7: 7000 | AU7: 570600024 | AV7: 13573219881 | AW7: 143 | AX7: 5 | AY7: 1307 | AZ7: 0.05 | BA7: 10 | BB7: 0.051 | BC7: Semi Urban | BD7: Core | BE7: Semi Urban Core | BF7: Winner | BG7: 4 | BH7: 4 | BI7: 4 | BJ7: 2 | BK7: 0.0016 | BL7: 95 | BM7: 5 | BN7: 16.29
A8: KABACO MBARARA | B8: BKAB005 | C8: CHARITY TUSIIME | D8: Distribution Centre | E8: CHARITY TUSIIME | F8: MANAGER | G8: 772816012 | H8: 772816012 | I8: 772816012 | J8: kabacougltd@yahoo.com | K8: RUTI | L8: MBARARA | M8: -0.608141 | N8: 30.563436 | O8: T | P8: Mon-Sun | Q8: 7 | R8: X | S8: X | T8: X | U8: X | V8: X | W8: X | X8: X | Y8: 20 | Z8: 0800-1700 | AA8: Susan Twongyeirwe | AB8: Steven R. Bazungu | AC8: 1 | AD8: 50000 | AE8: 33232 | AF8: 240 | AG8: 0 | AH8: 1904117805 | AI8: Mon | AJ8: Tue | AK8: Wed | AL8: Thu | AM8: Fri | AN8: Sat | AO8: Sun | AP8: Mon Tue Wed Thu Fri Sat Sun | AQ8: 10 | AR8: 324252 | AS8: Own | AT8: 7000 | AU8: 15642972 | AV8: 10187466025 | AW8: 138 | AX8: 68 | AY8: 48 | AZ8: 0.04 | BA8: 2 | BB8: 0.036 | BC8: Semi Urban | BD8: Value | BE8: Semi Urban Value | BF8: Basic | BG8: 3 | BH8: 3 | BI8: 4 | BJ8: 1 | BK8: 0.0064 | BM8: 5 | BN8: 2.67
A9: KATO INVESTMENT BULENGA | B9: KKAT010 | C9: MATOVU FAHAD | D9: Distribution Centre | E9: MATOVU FAHAD | F9: MANAGER | G9: 777358546 | H9: 777358546 | I9: 777358546 | J9: Katoinvestmentslimited@yahoo.com | K9: BULENGA | L9: BULENGA | M9: 0.32629667 | N9: 32.500112 | O9: T | P9: Mon-Sun | Q9: 7 | R9: X | S9: X | T9: X | U9: X | V9: X | W9: X | X9: X | Y9: 20 | Z9: 0800-1700 | AA9: Ronald Kasumba | AB9: Ronald Kasumba | AC9: 1 | AD9: 15000 | AE9: 23251 | AF9: 169 | AG9: 0 | AH9: 1366003205 | AI9: Mon | AJ9: Tue | AK9: Wed | AL9: Thu | AM9: Fri | AN9: Sat | AO9: Sun | AP9: Mon Tue Wed Thu Fri Sat Sun | AQ9: 930 | AR9: 228238 | AS9: 3PL | AT9: 6447 | AU9: 610400408 | AV9: 7055644094 | AW9: 138 | AX9: 2 | AY9: 2674 | AZ9: 0.03 | BA9: 20 | BB9: 0.025 | BC9: Urban | BD9: Core | BE9: Urban Core | BF9: Winner | BG9: 2 | BH9: 2 | BI9: 2 | BJ9: 1 | BK9: 0.0008 | BL9: 40 | BM9: 5 | BN9: 7.43
A10: KATO INVESTMENT KAGADI | B10: KKAT003 | C10: Nasuna Florence | D10: Distributor CENTER | E10: Nasuna Florence | F10: MANAGER | G10: 782593227 | H10: 781472462 | I10: 781472462 | J10: Katoinvestmentslimited@yahoo.com | K10: KAGADI | L10: KAGADI | M10: 0.93529333 | N10: 30.814132 | O10: T | P10: Mon-Sun | Q10: 7 | R10: X | S10: X | T10: X | U10: X | V10: X | W10: X | X10: X | Y10: 20 | Z10: 0800-1700 | AA10: Ronald Kasumba | AB10: Ronald Kasumba | AC10: 1 | AD10: 20000 | AE10: 25392 | AF10: 184 | AG10: 0 | AH10: 916794238 | AI10: Mon | AJ10: Tue | AK10: Wed | AL10: Thu | AM10: Fri | AN10: Sat | AO10: Sun | AP10: Mon Tue Wed Thu Fri Sat Sun | AQ10: 298 | AR10: 248231 | AS10: 3PL | AT10: 6922 | AU10: 852723846 | AV10: 7048800085 | AW10: 138 | AX10: 2 | AY10: 3435 | AZ10: 0.03 | BA10: 26 | BB10: 0.028 | BC10: Rural | BD10: Value | BE10: Rural Value | BF10: Low | BG10: 2 | BH10: 2 | BI10: 1 | BJ10: 1 | BK10: 0.0009 | BL10: -1 | BM10: 5 | BN10: 1.43
A11: KATO INVESTMENT KAKUMIRO | B11: KKAT013 | C11: NANSUBUGA LUCIE | D11: Distribution Centre | E11: NANSUBUGA LUCIE | F11: MANAGER | G11: 782666861 | H11: 782666861 | I11: 782666861 | J11: Katoinvestmentslimited@yahoo.com | K11: KAKUMIRO | L11: KAKUMIRO | M11: 0.77657167 | N11: 31.323683 | O11: T | P11: Mon-Sun | Q11: 7 | R11: X | S11: X | T11: X | U11: x | V11: X | W11: x | X11: X | Y11: 20 | Z11: 0800-1700 | AA11: Ronald Kasumba | AB11: Ronald Kasumba | AC11: 1 | AD11: 15000 | AE11: 16097 | AF11: 113 | AG11: 0 | AH11: 570240618 | AI11: Mon | AJ11: Tue | AK11: Wed | AL11: Thu | AM11: Fri | AN11: Sat | AO11: Sun | AP11: Mon Tue Wed Thu Fri Sat Sun | AQ11: 304 | AR11: 153035 | AS11: 3PL | AT11: 5794 | AU11: 610822594 | AV11: 4654532750 | AW11: 142 | AX11: 1 | AY11: 3991 | AZ11: 0.02 | BA11: 28 | BB11: 0.018 | BC11: Rural | BD11: Value | BE11: Rural Value | BF11: Low | BG11: 2 | BH11: 2 | BI11: 1 | BJ11: 2 | BK11: 0.0006 | BL11: -56 | BM11: 5 | BN11: -6.29
A12: KATO INVESTMENT KALISIZO | B12: NKAT002 | C12: SIMON MAKODI | D12: Distribution Centre | E12: SIMON MAKODI | F12: MANAGER | G12: 777014145 | H12: 777014145 | I12: 777014145 | J12: Katoinvestmentslimited@yahoo.com | K12: KALISIZO | L12: KALISIZO | M12: -0.63392167 | N12: 31.542553 | O12: T | P12: Mon-Sun | Q12: 7 | R12: X | S12: X | T12: X | U12: X | V12: X | W12: X | X12: X | Y12: 20 | Z12: 0800-1700 | AA12: Susan Twongyeirwe | AB12: Susan Twongyeirwe | AC12: 1 | AD12: 27000 | AE12: 27641 | AF12: 214 | AG12: 0 | AH12: 1283853109 | AI12: Mon | AJ12: Tue | AK12: Wed | AL12: Thu | AM12: Fri | AN12: Sat | AO12: Sun | AP12: Mon Tue Wed Thu Fri Sat Sun | AQ12: 304 | AR12: 288577 | AS12: Own | AT12: - | AU12: 264515713 | AV12: 8388054767 | AW12: 129 | AX12: 4 | AY12: 917 | AZ12: 0.03 | BA12: 8 | BB12: 0.03 | BC12: Rural | BD12: Value | BE12: Rural Value | BF12: Basic | BG12: 3 | BH12: 3 | BI12: 4 | BJ12: 1 | BK12: 0.0016 | BM12: 5 | BN12: 2.67
A13: KATO INVESTMENT KATIKARA | B13: KKAT012 | C13: LUUTU JOSEPH | D13: Distribution Centre | E13: LUUTU JOSEPH | F13: MANAGER | G13: 787597266 | H13: 787597266 | I13: 787597266 | J13: Katoinvestmentslimited@yahoo.com | K13: KATIKARA | L13: KATIKARA | M13: 1.1480783 | N13: 31.284513 | O13: T | P13: Mon-Sun | Q13: 7 | R13: X | S13: X | T13: X | U13: X | V13: X | W13: X | X13: X | Y13: 20 | Z13: 0800-1700 | AA13: Ronald Kasumba | AB13: Ronald Kasumba | AC13: 1 | AD13: 20000 | AE13: 19321 | AF13: 135 | AG13: 0 | AH13: 749085617 | AI13: Mon | AJ13: Tue | AK13: Wed | AL13: Thu | AM13: Fri | AN13: Sat | AO13: Sun | AP13: Mon Tue Wed Thu Fri Sat Sun | AQ13: 252 | AR13: 181696 | AS13: 3PL | AT13: 7220 | AU13: 1010620741 | AV13: 5385847389 | AW13: 144 | AX13: 1 | AY13: 5562 | AZ13: 0.02 | BA13: 29 | BB13: 0.021 | BC13: Rural | BD13: Value | BE13: Rural Value | BF13: Low | BG13: 2 | BH13: 2 | BI13: 1 | BJ13: 3 | BK13: 0.001 | BL13: -27 | BM13: 5 | BN13: -2
A14: KATO INVESTMENT KYEGEGWA | B14: KKAT014 | C14: Ssemanda Herny | D14: Distributor CENTER | E14: Ssemanda Herny | F14: MANAGER | G14: 782685446 | H14: 782685446 | I14: 782685446 | J14: Katoinvestmentslimited@yahoo.com | K14: KYEGEGWA | L14: KYEGEGWA | M14: -0.480446 | N14: 31.057648 | O14: T | P14: Mon-Sun | Q14: 7 | R14: X | S14: X | T14: X | U14: X | V14: X | W14: X | X14: X | Y14: 20 | Z14: 0800-1700 | AA14: Ronald Kasumba | AB14: Ronald Kasumba | AC14: 1 | AD14: 8000 | AE14: 23684 | AF14: 180 | AG14: 0 | AH14: - | AI14: Mon | AJ14: Tue | AK14: Wed | AL14: Thu | AM14: Fri | AN14: Sat | AO14: Sun | AP14: Mon Tue Wed Thu Fri Sat Sun | AQ14: 630 | AR14: 242480 | AS14: 3PL | AT14: 5504 | AU14: 593115869 | AV14: 6520469909 | AW14: 132 | AX14: 2 | AY14: 2446 | AZ14: 0.02 | BA14: 19 | BB14: 0.026 | BC14: Rural | BD14: Value | BE14: Rural Value | BF14: Winner | BG14: 2 | BH14: 2 | BI14: 3 | BJ14: 1 | BK14: 0.0004 | BL14: 100 | BM14: 5 | BN14: 16.14
A15: KATO INVESTMENT MASAKA | B15: NKAT001 | C15: SIMON MAKODI | D15: Distribution Centre | E15: SIMON MAKODI | F15: MANAGER | G15: 777014145 | H15: 777014145 | I15: 777014145 | J15: Katoinvestmentslimited@yahoo.com | K15: MASAKA | L15: MASAKA | M15: -0.34422333 | N15: 31.739208 | O15: T | P15: Mon-Sun | Q15: 7 | R15: X | S15: X | T15: x | U15: X | V15: X | W15: X | X15: X | Y15: 20 | Z15: 0800-1700 | AA15: Susan Twongyeirwe | AB15: Susan Twongyeirwe | AC15: 1 | AD15: 35000 | AE15: 64058 | AF15: 459 | AG15: 0 | AH15: 2237641608 | AI15: Mon | AJ15: Tue | AK15: Wed | AL15: Thu | AM15: Fri | AN15: Sat | AO15: Sun | AP15: Mon Tue Wed Thu Fri Sat Sun | AQ15: 560 | AR15: 620159 | AS15: Own | AT15: 7000 | AU15: 445785551 | AV15: 19598862486 | AW15: 139 | AX15: 5 | AY15: 719 | AZ15: 0.07 | BA15: 6 | BB15: 0.07 | BC15: Urban | BD15: Core | BE15: Urban Core | BF15: Winner | BG15: 4 | BH15: 4 | BI15: 4 | BJ15: 1 | BK15: 0.0015 | BL15: 88 | BM15: 5 | BN15: 15.14
A16: KATO INVESTMENT MASAKA - SEMBABULE | B16: NKAT001 | C16: SIMON MAKODI | D16: Distribution Centre | E16: SIMON MAKODI | F16: MANAGER | G16: 777014145 | H16: 777014145 | I16: 777014145 | J16: Katoinvestmentslimited@yahoo.com | K16: MASAKA | L16: MASAKA | M16: -0.0819461 | N16: 31.458185 | O16: T | P16: Mon-Sun | Q16: 7 | R16: X | S16: X | T16: x | U16: X | V16: X | W16: X | X16: X | Y16: 20 | Z16: 0800-1700 | AA16: Susan Twongyeirwe | AB16: Susan Twongyeirwe | AC16: 1 | AF16: - | AG16: 0 | AH16: 2237641608 | AI16: Mon | AJ16: Tue | AK16: Wed | AL16: Thu | AM16: Fri | AN16: Sat | AO16: Sun | AP16: Mon Tue Wed Thu Fri Sat Sun | AQ16: 448 | AS16: Own | AT16: 7000 | AU16: - | BC16: Rural | BD16: Value | BE16: Rural Value | BF16: Winner | BM16: 5 | BN16: 5
A17: KATO INVESTMENT MIT - BUKUYA | B17: KKAT006 | C17: MUTUMBA ALLOYZIOUS | D17: Distribution Centre | E17: MUTUMBA ALLOYZIOUS | F17: MANAGER | G17: 789446768 | H17: 789446768 | I17: 789446768 | J17: Katoinvestmentslimited@yahoo.com | K17: BUKUYA | L17: BUKUYA | M17: 0.6743816 | N17: 31.836002 | O17: T | P17: Mon-Sun | Q17: 7 | R17: X | S17: X | T17: X | U17: X | V17: X | W17: X | X17: X | Y17: 20 | Z17: 0800-1700 | AA17: Ronald Kasumba | AB17: Ronald Kasumba | AC17: 1 | AF17: - | AG17: 0 | AH17: 1976369683 | AI17: Mon | AJ17: Tue | AK17: Wed | AL17: Thu | AM17: Fri | AN17: Sat | AO17: Sun | AP17: Mon Tue Wed Thu Fri Sat Sun | AQ17: 448 | AS17: 3PL | AT17: 6702 | AU17: - | BC17: Rural | BD17: Value | BE17: Rural Value | BF17: Winner | BM17: 5 | BN17: 5
A18: KATO INVESTMENT MITYANA | B18: KKAT006 | C18: MUTUMBA ALLOYZIOUS | D18: Distribution Centre | E18: MUTUMBA ALLOYZIOUS | F18: MANAGER | G18: 789446768 | H18: 789446768 | I18: 789446768 | J18: Katoinvestmentslimited@yahoo.com | K18: MITYANA | L18: MITYANA | M18: 0.399595 | N18: 32.043932 | O18: T | P18: Mon-Sun | Q18: 7 | R18: X | S18: X | T18: X | U18: X | V18: X | W18: X | X18: X | Y18: 20 | Z18: 0800-1700 | AA18: Ronald Kasumba | AB18: Ronald Kasumba | AC18: 1 | AD18: 55000 | AE18: 62605 | AF18: 467 | AG18: 0 | AH18: 1976369683 | AI18: Mon | AJ18: Tue | AK18: Wed | AL18: Thu | AM18: Fri | AN18: Sat | AO18: Sun | AP18: Mon Tue Wed Thu Fri Sat Sun | AQ18: 448 | AR18: 629793 | AS18: 3PL | AT18: 6702 | AU18: 2157322692 | AV18: 18293893807 | AW18: 134 | AX18: 2 | AY18: 3425 | AZ18: 0.07 | BA18: 25 | BB18: 0.069 | BC18: Semi Urban | BD18: Value | BE18: Semi Urban Value | BF18: Winner | BG18: 4 | BH18: 4 | BI18: 1 | BJ18: 1 | BK18: 0.0046 | BL18: 38 | BM18: 5 | BN18: 7.57
A19: KATO INVESTMENT MUBENDE | B19: KKAT007 | C19: NAKYAMBADDE DAPHINE | D19: Distribution Centre | E19: NAKYAMBADDE DAPHINE | F19: MANAGER | G19: 70072790 | H19: 787560468 | I19: 787560468 | J19: Katoinvestmentslimited@yahoo.com | K19: MUBENDE | L19: MUBENDE | M19: 2.5327967 | N19: 31.841195 | O19: T | P19: Mon-Sun | Q19: 7 | R19: X | S19: X | T19: X | U19: X | V19: X | W19: X | X19: X | Y19: 20 | Z19: 0800-1700 | AA19: Ronald Kasumba | AB19: Ronald Kasumba | AC19: 1 | AD19: 60000 | AE19: 44106 | AF19: 318 | AG19: 0 | AH19: 1822785369 | AI19: Mon | AJ19: Tue | AK19: Wed | AL19: Thu | AM19: Fri | AN19: Sat | AO19: Sun | AP19: Mon Tue Wed Thu Fri Sat Sun | AQ19: 1040 | AR19: 429219 | AS19: 3PL | AT19: 5794 | AU19: 1252648141 | AV19: 12651041784 | AW19: 139 | AX19: 2 | AY19: 2918 | AZ19: 0.05 | BA19: 22 | BB19: 0.048 | BC19: Semi Urban | BD19: Value | BE19: Semi Urban Value | BF19: Winner | BG19: 3 | BH19: 3 | BI19: 2 | BJ19: 1 | BK19: 0.0006 | BL19: 91 | BM19: 5 | BN19: 15
A20: KATO MASAKA - KALANGALA | B20: NKAT001 | C20: SIMON MAKODI | D20: Distributor CENTER | E20: SIMON MAKODI | F20: MANAGER | G20: 777014145 | H20: 777014145 | I20: 777014145 | J20: Katoinvestmentslimited@yahoo.com | K20: KALANGALA | L20: KALANGALA | M20: -0.32294833 | N20: 32.28909 | O20: T | P20: Mon-Sun | Q20: 7 | R20: X | S20: X | T20: X | U20: X | V20: X | W20: X | X20: X | Y20: 20 | Z20: 0800-1700 | AA20: Susan Twongyeirwe | AB20: Susan Twongyeirwe | AC20: 1 | AD20: 3000 | AF20: - | AG20: 0 | AH20: 250945008 | AI20: Mon | AJ20: Tue | AK20: Wed | AL20: Thu | AM20: Fri | AN20: Sat | AO20: Sun | AP20: Mon Tue Wed Thu Fri Sat Sun | AQ20: 670 | AS20: Own | AT20: 7000 | AU20: - | BC20: Rural | BD20: Core | BE20: Rural Core | BF20: Winner | BM20: 5 | BN20: 5
A21: KIHEMBE BUSHENYI | B21: NKIH002 | C21: LABAN | D21: Distributor CENTER | E21: Musinguzi Laban | F21: MANAGER | G21: 772381421 | H21: 772381421 | I21: 772381421 | J21: kihembebrothers@gmail.com | K21: KIHEMBE | L21: KIHEMBE | M21: -0.54070833 | N21: 30.188145 | O21: T | P21: Mon-Sun | Q21: 7 | R21: X | S21: X | T21: X | U21: X | V21: X | W21: X | X21: X | Y21: 20 | Z21: 0800-1700 | AA21: Susan Twongyeirwe | AB21: Susan Twongyeirwe | AC21: 1 | AD21: 25000 | AE21: 39888 | AF21: 280 | AG21: 0 | AH21: 1605852878 | AI21: Mon | AJ21: Tue | AK21: Wed | AL21: Thu | AM21: Fri | AN21: Sat | AO21: Sun | AP21: Mon Tue Wed Thu Fri Sat Sun | AQ21: 600 | AR21: 377328 | AS21: Own | AT21: - | AU21: 103760182 | AV21: 11849734000 | AW21: 143 | AX21: 12 | AY21: 275 | AZ21: 0.04 | BA21: 3 | BB21: 0.044 | BC21: Rural | BD21: Value | BE21: Rural Value | BF21: Winner | BG21: 3 | BH21: 3 | BI21: 4 | BJ21: 2 | BK21: 0.0105 | BL21: 100 | BM21: 5 | BN21: 16.72
A22: kIHEMBE IBANDA | B22: NIBA001 | C22: LABAN | D22: Distributor CENTER | E22: Musinguzi Laban | F22: MANAGER | G22: 772381421 | H22: 772381421 | I22: 772381421 | J22: kihembebrothers@gmail.com | K22: IBANDA | L22: IBANDA | M22: -0.134147 | N22: 30.494324 | O22: T | P22: Mon-Sun | Q22: 7 | R22: X | S22: X | T22: X | U22: X | V22: X | W22: X | X22: X | Y22: 20 | Z22: 0800-1700 | AA22: Susan Twongyeirwe | AB22: Susan Twongyeirwe | AC22: 1 | AD22: 16700 | AE22: 24122 | AF22: 175 | AG22: 0 | AH22: 808654057 | AI22: Mon | AJ22: Tue | AK22: Wed | AL22: Thu | AM22: Fri | AN22: Sat | AO22: Sun | AP22: Mon Tue Wed Thu Fri Sat Sun | AQ22: 0 | AR22: 236100 | AS22: Own | AT22: - | AU22: 94538835 | AV22: 7219224145 | AW22: 138 | AX22: 8 | AY22: 400 | AZ22: 0.03 | BA22: 5 | BB22: 0.026 | BC22: Rural | BD22: Core | BE22: Rural Core | BF22: Basic | BG22: 2 | BH22: 2 | BI22: 4 | BJ22: 1 | BK22: 0.0017 | BL22: 0 | BM22: 5 | BN22: 2
A23: KIHEMBE MBARARA | B23: NKIH001 | C23: LABAN | D23: Distribution Centre | E23: Musinguzi Laban | F23: MANAGER | G23: 772381421 | H23: 772381421 | I23: 772381421 | J23: kihembebrothers@gmail.com | K23: KAKOBA | L23: MBARARA | M23: -0.608141 | N23: 30.676364 | O23: T | P23: Mon-Sun | Q23: 7 | R23: X | S23: X | T23: X | U23: X | V23: X | W23: X | X23: X | Y23: 20 | Z23: 0800-1700 | AA23: Susan Twongyeirwe | AB23: Susan Twongyeirwe | AC23: 1 | AD23: 60000 | AE23: 51444 | AF23: 368 | AG23: 0 | AH23: 2680678845 | AI23: Mon | AJ23: Tue | AK23: Wed | AL23: Thu | AM23: Fri | AN23: Sat | AO23: Sun | AP23: Mon Tue Wed Thu Fri Sat Sun | AQ23: 0 | AR23: 496413 | AS23: Own | AT23: 7000 | AU23: 23948585 | AV23: 15582636550 | AW23: 139.9 | AX23: 68 | AY23: 48 | AZ23: 0.06 | BA23: 1 | BB23: 0.056 | BC23: Urban | BD23: Core | BE23: Urban Core | BF23: Winner | BG23: 4 | BH23: 4 | BI23: 4 | BJ23: 1 | BL23: 86 | BM23: 5 | BN23: 17.33
A24: KIHEMBE MBRA-LYANTONDE | B24: NKIH001 | C24: CYNTHIA | D24: Distribution Centre | E24: CYNTHIA | F24: MANAGER | G24: 703110134 | H24: 703110134 | I24: 703110134 | J24: kihembebrothers@gmail.com | K24: LYANTONDE | L24: LYANTONDE | M24: 0.451316 | N24: 31.156547 | O24: T | P24: Mon-Sun | Q24: 7 | R24: X | S24: X | T24: X | U24: X | V24: X | W24: X | X24: X | Y24: 20 | Z24: 0800-1700 | AA24: Susan Twongyeirwe | AB24: Susan Twongyeirwe | AC24: 1 | AD24: 31000 | AF24: - | AG24: 0 | AH24: 59346174 | AI24: Mon | AJ24: Tue | AK24: Wed | AL24: Thu | AM24: Fri | AN24: Sat | AO24: Sun | AP24: Mon Tue Wed Thu Fri Sat Sun | AQ24: 0 | AS24: Own | AT24: 7000 | AU24: - | BC24: Rural | BD24: Value | BE24: Rural Value | BF24: Winner | BM24: 5 | BN24: 5
A25: KOBUSINGYE FORTPORTAL | B25: BKOB003 | C25: KENNETH | D25: Distribution Centre | E25: KENNETH | F25: MANAGER | G25: 752490085 | H25: 752490085 | I25: 752490085 | J25: Kobusingyeandsonsdistributors@gmail.com | K25: FORTPORTAL | L25: FORTPORTAL | M25: 0.658825 | N25: 30.274965 | O25: T | P25: Mon-Sun | Q25: 7 | R25: X | S25: X | T25: x | U25: X | V25: x | W25: x | X25: X | Y25: 20 | Z25: 0800-1700 | AA25: Steven R. Bazungu | AB25: Steven R. Bazungu | AC25: 1 | AD25: 20000 | AE25: 31404 | AF25: 217 | AG25: 0 | AH25: 1274805685 | AI25: Mon | AJ25: Tue | AK25: Wed | AL25: Thu | AM25: Fri | AN25: Sat | AO25: Sun | AP25: Mon Tue Wed Thu Fri Sat Sun | AQ25: 680 | AR25: 293251 | AS25: 3PL | AT25: 7000 | AU25: 462250947 | AV25: 9158324226 | AW25: 145 | AX25: 4 | AY25: 1576 | AZ25: 0.03 | BA25: 12 | BB25: 0.034 | BC25: Urban | BD25: Value | BE25: Urban Value | BF25: Winner | BG25: 3 | BH25: 3 | BI25: 4 | BJ25: 4 | BK25: 0.0011 | BL25: 94 | BM25: 5 | BN25: 16.14
A26: KOBUSINGYE KAMWENGE | B26: BKOB004 | C26: PETER KINGOMA | D26: Distribution Centre | E26: PETER KINGOMA | F26: MANAGER | G26: 772373106 | H26: 701373106 | I26: 701373106 | J26: Kobusingyeandsonsdistributors@gmail.com | K26: KAMWENGE | L26: KAMWENGE | M26: 0.17469167 | N26: 30.448238 | O26: T | P26: Mon-Sun | Q26: 7 | R26: X | S26: X | T26: X | U26: X | V26: X | W26: X | X26: X | Y26: 20 | Z26: 0800-1700 | AA26: Steven R. Bazungu | AB26: Steven R. Bazungu | AC26: 1 | AD26: 16000 | AE26: 13468 | AF26: 91 | AG26: 0 | AH26: 540278362 | AI26: Mon | AJ26: Tue | AK26: Wed | AL26: Thu | AM26: Fri | AN26: Sat | AO26: Sun | AP26: Mon Tue Wed Thu Fri Sat Sun | AQ26: 304 | AR26: 122669 | AS26: 3PL | AT26: 7000 | AU26: 145022192 | AV26: 3866850669 | AW26: 148 | AX26: 6 | AY26: 1182 | AZ26: 0.01 | BA26: 9 | BB26: 0.015 | BC26: Rural | BD26: Value | BE26: Rural Value | BF26: Winner | BG26: 2 | BH26: 2 | BI26: 4 | BJ26: 4 | BK26: 0.0013 | BL26: 100 | BM26: 5 | BN26: 16.71
A27: KOBUSINGYE KYENJOJO | B27: BKOB001 | C27: PAUL MUGISA | D27: Distribution Centre | E27: PAUL MUGISA | F27: MANAGER | G27: 774821010 | H27: 754821010 | I27: 754821010 | J27: Kobusingyeandsonsdistributors@gmail.com | K27: KYENJOJO | L27: KYENJOJO | M27: 0.61723 | N27: 30.63615 | O27: T | P27: Mon-Sun | Q27: 7 | R27: X | S27: X | T27: X | U27: X | V27: X | W27: X | X27: X | Y27: 20 | Z27: 0800-1700 | AA27: Steven R. Bazungu | AB27: Steven R. Bazungu | AC27: 1 | AD27: 18000 | AE27: 23524 | AF27: 166 | AG27: 0 | AH27: 989217173 | AI27: Mon | AJ27: Tue | AK27: Wed | AL27: Thu | AM27: Fri | AN27: Sat | AO27: Sun | AP27: Mon Tue Wed Thu Fri Sat Sun | AQ27: 228 | AR27: 224369 | AS27: 3PL | AT27: 7000 | AU27: 674769064 | AV27: 6664209688 | AW27: 142 | AX27: 2 | AY27: 3007 | AZ27: 0.03 | BA27: 24 | BB27: 0.026 | BC27: Rural | BD27: Value | BE27: Rural Value | BF27: Winner | BG27: 2 | BH27: 2 | BI27: 1 | BJ27: 2 | BK27: 0.0008 | BL27: 100 | BM27: 5 | BN27: 16
A28: NTALE & SONS KAKIRI | B28: KNTA004 | C28: HAKIM | D28: Distributor CENTER | E28: HAKIM | F28: MANAGER | G28: 777408645 | H28: 777408645 | I28: 777408645 | J28: nntaleandsons@yahoo.com | K28: KAKIRI | L28: KAKIRI | M28: 0.41922 | N28: 32.401003 | O28: T | P28: Mon-Sun | Q28: 7 | R28: X | S28: X | T28: X | U28: X | V28: X | W28: X | X28: X | Y28: 20 | Z28: 0800-1700 | AA28: Gerald Mugisa | AB28: Gerald Mugisa | AC28: 1 | AD28: 16000 | AE28: 27898 | AF28: 197 | AG28: 0 | AH28: 748793906 | AI28: Mon | AJ28: Tue | AK28: Wed | AL28: Thu | AM28: Fri | AN28: Sat | AO28: Sun | AP28: Mon Tue Wed Thu Fri Sat Sun | AQ28: 620 | AR28: 265436 | AS28: 3PL | AT28: 8678 | AU28: 1057919540 | AV28: 8225918215 | AW28: 142 | AX28: 2 | AY28: 3986 | AZ28: 0.03 | BA28: 27 | BB28: 0.031 | BC28: Semi Urban | BD28: Core | BE28: Semi Urban Core | BF28: Winner | BG28: 3 | BH28: 3 | BI28: 1 | BJ28: 2 | BK28: 0.0003 | BL28: 17 | BM28: 5 | BN28: 4.43
A29: NTALE AND SONS KIBOGA | B29: KNTA002 | C29: HAKIM | D29: Distribution Centre | E29: HAKIM | F29: MANAGER | G29: 777408645 | H29: 777408645 | I29: 777408645 | J29: nntaleandsons@yahoo.com | K29: KIBOGA | L29: KIBOGA | M29: 0.91794666 | N29: 31.763598 | O29: T | P29: Mon-Sun | Q29: 7 | R29: X | S29: X | T29: X | U29: X | V29: X | W29: X | X29: X | Y29: 20 | Z29: 0800-1700 | AA29: Gerald Mugisa | AB29: Gerald Mugisa | AC29: 1 | AD29: 50000 | AE29: 33221 | AF29: 239 | AG29: 0 | AH29: 1252132420 | AI29: Mon | AJ29: Tue | AK29: Wed | AL29: Thu | AM29: Fri | AN29: Sat | AO29: Sun | AP29: Mon Tue Wed Thu Fri Sat Sun | AQ29: 810 | AR29: 322310 | AS29: Own | AT29: 6119 | AU29: 629746453 | AV29: 9463844113 | AW29: 139 | AX29: 2 | AY29: 1954 | AZ29: 0.04 | BA29: 14 | BB29: 0.036 | BC29: Semi Urban | BD29: Value | BE29: Semi Urban Value | BF29: Winner | BG29: 3 | BH29: 3 | BI29: 4 | BJ29: 1 | BK29: 0.002 | BL29: 100 | BM29: 5 | BN29: 16.57
A30: RUGOMA KIHIHI | B30: BRUG004 | C30: Gloria | D30: Distributor CENTER | E30: Gloria | F30: MANAGER | G30: 788795147 | H30: 788795147 | I30: 788795147 | J30: rugoma10@yahoo.com | K30: KIHIHI | L30: KIHIHI | M30: -0.74765 | N30: 29.701378 | O30: T | P30: Mon-Sun | Q30: 7 | R30: X | S30: X | T30: X | U30: X | V30: X | W30: X | X30: X | Y30: 20 | Z30: 0800-1700 | AA30: Samuel Kenneth Ssekajja | AB30: Samuel Kenneth Ssekajja | AC30: 1 | AD30: 11000 | AE30: 14869 | AF30: 101 | AG30: 0 | AH30: 647108024 | AI30: Mon | AJ30: Tue | AK30: Wed | AL30: Thu | AM30: Fri | AN30: Sat | AO30: Sun | AP30: Mon Tue Wed Thu Fri Sat Sun | AQ30: 414 | AR30: 136277 | AS30: 3PL | AT30: 7000 | AU30: 292542037 | AV30: 4239747759 | AW30: 147 | AX30: 3 | AY30: 2147 | AZ30: 0.02 | BA30: 15 | BB30: 0.016 | BC30: Rural | BD30: Core | BE30: Rural Core | BF30: Basic | BG30: 2 | BH30: 2 | BI30: 3 | BJ30: 4 | BK30: 0.0185 | BL30: 0 | BM30: 5 | BN30: 2.29
A31: RUGOMA NTUNGAMO | B31: NRUG001 | C31: Muhwezi | D31: Distribution Centre | E31: Muhwezi | F31: OWNER | G31: 772402558 | H31: 772402558 | I31: 772402558 | J31: rugoma10@yahoo.com | K31: NTUNGAMO | L31: NTUNGAMO | M31: -0.87131833 | N31: 30.267212 | O31: T | P31: Mon-Sun | Q31: 7 | R31: X | S31: X | T31: X | U31: X | V31: X | W31: X | X31: X | Y31: 20 | Z31: 0800-1700 | AA31: Samuel Kenneth Ssekajja | AB31: Samuel Kenneth Ssekajja | AC31: 1 | AD31: 30000 | AE31: 25190 | AF31: 188 | AG31: 0 | AH31: 780064304 | AI31: Mon | AJ31: Tue | AK31: Wed | AL31: Thu | AM31: Fri | AN31: Sat | AO31: Sun | AP31: Mon Tue Wed Thu Fri Sat Sun | AQ31: 256 | AR31: 253378 | AS31: Own | AT31: 7000 | AU31: 88011165 | AV31: 7325474784 | AW31: 134 | AX31: 9 | AY31: 347 | AZ31: 0.03 | BA31: 4 | BB31: 0.028 | BC31: Rural | BD31: Value | BE31: Rural Value | BF31: Basic | BG31: 2 | BH31: 2 | BI31: 4 | BJ31: 1 | BK31: 0.0021 | BL31: 0 | BM31: 5 | BN31: 2
A32: RUGOMA RUKUNGIRI | B32: BRUG002 | C32: Muhwezi | D32: Distributor CENTER | E32: Muhwezi | F32: OWNER | G32: 772402558 | H32: 772402558 | I32: 772402558 | J32: rugoma10@yahoo.com | K32: RUKUNGIRI | L32: RUKUNGIRI | M32: -0.78682833 | N32: 29.926212 | O32: T | P32: Mon-Sun | Q32: 7 | R32: X | S32: X | T32: X | U32: X | V32: X | W32: X | X32: X | Y32: 20 | Z32: 0800-1700 | AA32: Samuel Kenneth Ssekajja | AB32: Samuel Kenneth Ssekajja | AC32: 1 | AD32: 9000 | AE32: 20173 | AF32: 141 | AG32: 0 | AH32: 529488616 | AI32: Mon | AJ32: Tue | AK32: Wed | AL32: Thu | AM32: Fri | AN32: Sat | AO32: Sun | AP32: Mon Tue Wed Thu Fri Sat Sun | AQ32: 144 | AR32: 190617 | AS32: 3PL | AT32: 7000 | AU32: 253026021 | AV32: 5941063928 | AW32: 143 | AX32: 5 | AY32: 1327 | AZ32: 0.02 | BA32: 11 | BB32: 0.022 | BC32: Semi Urban | BD32: Value | BE32: Semi Urban Value | BF32: Winner | BG32: 2 | BH32: 2 | BI32: 4 | BJ32: 2 | BK32: 0.001 | BL32: 100 | BM32: 5 | BN32: 16.43
A33: SAWAN KAYABWE | B33: KSAW005 | C33: GODWINE TINKA | D33: Distributor CENTER | E33: GODWINE TINKA | F33: MANAGER | G33: 0702774004 / 0776863785 | H33: 0702774004 / 0776863785 | I33: 0702774004 / 0776863785 | J33: godwinetinkah@gmail.com | K33: KAYABWE | L33: KAYABWE | M33: 0.014734 | N33: 32.029183 | O33: T | P33: Mon-Sun | Q33: 7 | R33: X | S33: X | T33: X | U33: X | V33: X | W33: X | X33: X | Y33: 20 | Z33: 0800-1700 | AA33: Peter Jumba | AB33: Peter Jumba | AC33: 1 | AD33: 10000 | AE33: 32672 | AF33: 237 | AG33: 0 | AH33: - | AI33: Mon | AJ33: Tue | AK33: Wed | AL33: Thu | AM33: Fri | AN33: Sat | AO33: Sun | AP33: Mon Tue Wed Thu Fri Sat Sun | AQ33: 382 | AR33: 319987 | AS33: 3PL | AT33: 6387 | AU33: 578300836 | AV33: 9757050161 | AW33: 138 | AX33: 4 | AY33: 1807 | AZ33: 0.04 | BA33: 13 | BB33: 0.036 | BC33: Semi Urban | BD33: Core | BE33: Semi Urban Core | BF33: Winner | BG33: 3 | BH33: 3 | BI33: 4 | BJ33: 1 | BK33: 0.013 | BL33: 35 | BM33: 5 | BN33: 7.29
A34: SAWAN NABBINGO | B34: KSAW004 | C34: SANJAY | D34: Distributor CENTER | E34: SANJAY | F34: MANAGER | G34: 0703584358 | H34: 0703584358 | I34: 0703584358 | J34: sanjaymkeshwala@keshwalagroup.com | K34: NABBINGO | L34: NABBINGO | M34: 0.278101 | N34: 32.47779 | O34: T | P34: Mon-Sun | Q34: 7 | R34: X | S34: X | T34: X | U34: X | V34: X | W34: X | X34: X | Y34: 20 | Z34: 0800-1700 | AA34: Peter Jumba | AB34: Peter Jumba | AC34: 1 | AD34: 12000 | AE34: 40147 | AF34: 289 | AG34: 0 | AH34: - | AI34: Mon | AJ34: Tue | AK34: Wed | AL34: Thu | AM34: Fri | AN34: Sat | AO34: Sun | AP34: Mon Tue Wed Thu Fri Sat Sun | AQ34: 516 | AR34: 390203 | AS34: 3PL | AT34: 7232 | AU34: 1078600207 | AV34: 8642399495 | AW34: 139 | AX34: 3 | AY34: 2764 | AZ34: 0.03 | BA34: 21 | BB34: 0.044 | BC34: Urban | BD34: Core | BE34: Urban Core | BF34: Winner | BG34: 3 | BH34: 3 | BI34: 2 | BJ34: 1 | BK34: 0.0065 | BL34: 84 | BM34: 5 | BN34: 14
AE35: 912023 | AF35: 6546 | AQ35: 2822141 | AR35: 8836900 | AU35: 16857893665 | AV35: 265562295400 | AW35: 139.3 | AX35: 3.1 | AY35: 1908 | AZ35: 1 | BB35: 1

Sheet Logs Tar
A1: Month | D1: LOGISTICS DAILY MEETING
A2: Week
A3: Day
A4: Date
A5: LAGGING INDICATOR | B5: Accountable | C5: KPI | D5: UN | E5: Trigger | F5: Target | G5: MTD
A6: SIO WHSE (VPO) | C6: LTI | D6: # | E6: <35 | F6: 35
A7: SIO DEL ( DPO) | C7: LTI | D7: # | E7: <8 | F7: 35
A8: T2 DWH | C8: LTI | D8: # | E8: >0 | F8: 0
A9: OWD WHSE (Management & Shop floor) | C9: TP | D9: # | E9: 4 | F9: 4
A10: OWD DEL (Management & Drivers) | C10: TP | D10: # | E10: 4 | F10: 4
A11: T2 Truck Avail% | C11: AE | D11: % | E11: <97% | F11: 0.97
A12: T2 Ave Departure | C12: TP | D12: Min | E12: 46 | F12: 45
A13: Refusals vs Issued | C13: RTM | D13: % | E13: 0.44 | F13: 0.0044
A14: On-Time% | C14: OTIF | D14: % | E14: >1,2% | F14: 0.012
A15: Returns to Issue | C15: NPS | D15: % | E15: <97% | F15: >99%
A16: Sunstone | D16: % | E16: <84% | F16: >90%
A17: Inv Accuracy | D17: % | E17: <85 | F17: >90%
A18: T1/T2 Open Cycles | D18: Nm | E18: >1 | F18: 0
A19: Gains Fulls/Empties | D19: R | E19: 40k | F19: 40k
A20: Losses Fulls | D20: R | E20: 40k | F20: 40k
A21: Stock Posting Time | D21: nM | E21: >10:31 | F21: 0.4375
A22: ATCT | C22: VPO | D22: nM | E22: >225 | F22: <220 | G22: 230.88235
A23: DCBL | C23: VPO | D23: nM | E23: >45 | F23: <40 | G23: 7.4166667
A24: DLPA | C24: VPO | D24: % | E24: >95 | F24: 0.99 | G24: 87.388889
A25: Picking Productivty | C25: VPO | D25: % | E25: 175 | F25: 200

Sheet List
A1: 708888967
B2: Comment for Av. Departure Var | E2: Comment For ETA Var | H2: Comment for Service Time Var | K2: Comment for Ave TIR Var | N2: Comment for Av. Arrival Var
B3: Damaged stock replacement | K3: Customer Delays | N3: Freeze Window
B4: Delayed Check ins | K4: Ferry delays | N4: Traffic at gate
B5: Prolonged meeting. | K5: Truck Breakdown | N5: Staging
B6: unplanned trainings | K6: Unknown stops | N6: Fork Lift Breakdown
B7: Pre-Trip inspection defect closure | K7: Traffic jam | N7: Yard Clearing
B8: Reconcile stock count delays | K8: Delays at weigh Bridge | N8: Space constraint
B9: Weigh bridge delays | K9: Space Constraint at customer | N9: Faulty weigh bridge
B10: Late coming | K10: Spent an extra night at customer | N10: DJ failures
B11: DJ failures | K11: Road blockage due to accidents | N11: Stock take
B12: Early Arrival | K12: Government Road block checks | N12: Delayed gate checks
B13: Traffic at the exit gate | K13: Truck diverted by transporter | N13: Delayed fuel
B14: Driver delays | K14: Conjestion at RD due to many trucks invoiced | N14: Offloading delays
B15: Delayed credit order release | K15: Planned to deliver to MDC
K16: Diverted for empty collection
Y366: Tr
